{
  "timestamp": "2025-09-16T22:30:09.603634",
  "system_stats": {
    "runtime_seconds": 291847.844399,
    "data_points_generated": 223020,
    "json_files_created": 50,
    "real_data_downloads": 0,
    "analytics_signals": 91316565,
    "generation_rate": 0.7641653151808038,
    "active_symbols": 20,
    "current_regime": "bear"
  },
  "signal_summary": {
    "total_signals": 145,
    "signal_types": {
      "volume_anomaly": 60,
      "high_volume": 25,
      "rsi_overbought": 60
    },
    "average_strength": 0.7532879978496517,
    "average_confidence": 0.8218845117027851,
    "timestamp": "2025-09-16T22:30:09.603728"
  },
  "active_signals": [
    {
      "signal_type": "volume_anomaly",
      "symbol": "MSFT",
      "timestamp": "2025-09-16T22:29:42.876652",
      "strength": 0.8896502600105249,
      "confidence": 1.0,
      "description": "Volume anomaly detected: 4.26\u03c3 deviation",
      "metadata": {
        "zscore": 4.260738400277628,
        "current_volume": 139863312,
        "mean_volume": 58167152.94736842
      }
    },
    {
      "signal_type": "high_volume",
      "symbol": "MSFT",
      "timestamp": "2025-09-16T22:29:42.876678",
      "strength": 0.553466389358483,
      "confidence": 0.4155764732973523,
      "description": "High volume: 2.25x average",
      "metadata": {
        "volume_ratio": 2.246729419892057,
        "interpretation": "increased_interest"
      }
    },
    {
      "signal_type": "volume_anomaly",
      "symbol": "MSFT",
      "timestamp": "2025-09-16T22:29:42.879695",
      "strength": 0.8896502600105249,
      "confidence": 1.0,
      "description": "Volume anomaly detected: 4.26\u03c3 deviation",
      "metadata": {
        "zscore": 4.260738400277628,
        "current_volume": 139863312,
        "mean_volume": 58167152.94736842
      }
    },
    {
      "signal_type": "high_volume",
      "symbol": "MSFT",
      "timestamp": "2025-09-16T22:29:42.879718",
      "strength": 0.553466389358483,
      "confidence": 0.4155764732973523,
      "description": "High volume: 2.25x average",
      "metadata": {
        "volume_ratio": 2.246729419892057,
        "interpretation": "increased_interest"
      }
    },
    {
      "signal_type": "volume_anomaly",
      "symbol": "MSFT",
      "timestamp": "2025-09-16T22:29:42.882589",
      "strength": 0.8896502600105249,
      "confidence": 1.0,
      "description": "Volume anomaly detected: 4.26\u03c3 deviation",
      "metadata": {
        "zscore": 4.260738400277628,
        "current_volume": 139863312,
        "mean_volume": 58167152.94736842
      }
    },
    {
      "signal_type": "high_volume",
      "symbol": "MSFT",
      "timestamp": "2025-09-16T22:29:42.882610",
      "strength": 0.553466389358483,
      "confidence": 0.4155764732973523,
      "description": "High volume: 2.25x average",
      "metadata": {
        "volume_ratio": 2.246729419892057,
        "interpretation": "increased_interest"
      }
    },
    {
      "signal_type": "volume_anomaly",
      "symbol": "MSFT",
      "timestamp": "2025-09-16T22:29:42.885382",
      "strength": 0.8896502600105249,
      "confidence": 1.0,
      "description": "Volume anomaly detected: 4.26\u03c3 deviation",
      "metadata": {
        "zscore": 4.260738400277628,
        "current_volume": 139863312,
        "mean_volume": 58167152.94736842
      }
    },
    {
      "signal_type": "high_volume",
      "symbol": "MSFT",
      "timestamp": "2025-09-16T22:29:42.885402",
      "strength": 0.553466389358483,
      "confidence": 0.4155764732973523,
      "description": "High volume: 2.25x average",
      "metadata": {
        "volume_ratio": 2.246729419892057,
        "interpretation": "increased_interest"
      }
    },
    {
      "signal_type": "volume_anomaly",
      "symbol": "MSFT",
      "timestamp": "2025-09-16T22:29:42.888139",
      "strength": 0.8896502600105249,
      "confidence": 1.0,
      "description": "Volume anomaly detected: 4.26\u03c3 deviation",
      "metadata": {
        "zscore": 4.260738400277628,
        "current_volume": 139863312,
        "mean_volume": 58167152.94736842
      }
    },
    {
      "signal_type": "high_volume",
      "symbol": "MSFT",
      "timestamp": "2025-09-16T22:29:42.888158",
      "strength": 0.553466389358483,
      "confidence": 0.4155764732973523,
      "description": "High volume: 2.25x average",
      "metadata": {
        "volume_ratio": 2.246729419892057,
        "interpretation": "increased_interest"
      }
    },
    {
      "signal_type": "volume_anomaly",
      "symbol": "MSFT",
      "timestamp": "2025-09-16T22:29:42.891049",
      "strength": 0.8896502600105249,
      "confidence": 1.0,
      "description": "Volume anomaly detected: 4.26\u03c3 deviation",
      "metadata": {
        "zscore": 4.260738400277628,
        "current_volume": 139863312,
        "mean_volume": 58167152.94736842
      }
    },
    {
      "signal_type": "high_volume",
      "symbol": "MSFT",
      "timestamp": "2025-09-16T22:29:42.891072",
      "strength": 0.553466389358483,
      "confidence": 0.4155764732973523,
      "description": "High volume: 2.25x average",
      "metadata": {
        "volume_ratio": 2.246729419892057,
        "interpretation": "increased_interest"
      }
    },
    {
      "signal_type": "volume_anomaly",
      "symbol": "MSFT",
      "timestamp": "2025-09-16T22:29:42.893899",
      "strength": 0.8896502600105249,
      "confidence": 1.0,
      "description": "Volume anomaly detected: 4.26\u03c3 deviation",
      "metadata": {
        "zscore": 4.260738400277628,
        "current_volume": 139863312,
        "mean_volume": 58167152.94736842
      }
    },
    {
      "signal_type": "high_volume",
      "symbol": "MSFT",
      "timestamp": "2025-09-16T22:29:42.893919",
      "strength": 0.553466389358483,
      "confidence": 0.4155764732973523,
      "description": "High volume: 2.25x average",
      "metadata": {
        "volume_ratio": 2.246729419892057,
        "interpretation": "increased_interest"
      }
    },
    {
      "signal_type": "volume_anomaly",
      "symbol": "MSFT",
      "timestamp": "2025-09-16T22:29:42.896764",
      "strength": 0.8896502600105249,
      "confidence": 1.0,
      "description": "Volume anomaly detected: 4.26\u03c3 deviation",
      "metadata": {
        "zscore": 4.260738400277628,
        "current_volume": 139863312,
        "mean_volume": 58167152.94736842
      }
    },
    {
      "signal_type": "high_volume",
      "symbol": "MSFT",
      "timestamp": "2025-09-16T22:29:42.896785",
      "strength": 0.553466389358483,
      "confidence": 0.4155764732973523,
      "description": "High volume: 2.25x average",
      "metadata": {
        "volume_ratio": 2.246729419892057,
        "interpretation": "increased_interest"
      }
    },
    {
      "signal_type": "volume_anomaly",
      "symbol": "MSFT",
      "timestamp": "2025-09-16T22:29:42.899584",
      "strength": 0.8896502600105249,
      "confidence": 1.0,
      "description": "Volume anomaly detected: 4.26\u03c3 deviation",
      "metadata": {
        "zscore": 4.260738400277628,
        "current_volume": 139863312,
        "mean_volume": 58167152.94736842
      }
    },
    {
      "signal_type": "high_volume",
      "symbol": "MSFT",
      "timestamp": "2025-09-16T22:29:42.899605",
      "strength": 0.553466389358483,
      "confidence": 0.4155764732973523,
      "description": "High volume: 2.25x average",
      "metadata": {
        "volume_ratio": 2.246729419892057,
        "interpretation": "increased_interest"
      }
    },
    {
      "signal_type": "volume_anomaly",
      "symbol": "MSFT",
      "timestamp": "2025-09-16T22:29:42.902925",
      "strength": 0.8896502600105249,
      "confidence": 1.0,
      "description": "Volume anomaly detected: 4.26\u03c3 deviation",
      "metadata": {
        "zscore": 4.260738400277628,
        "current_volume": 139863312,
        "mean_volume": 58167152.94736842
      }
    },
    {
      "signal_type": "high_volume",
      "symbol": "MSFT",
      "timestamp": "2025-09-16T22:29:42.902952",
      "strength": 0.553466389358483,
      "confidence": 0.4155764732973523,
      "description": "High volume: 2.25x average",
      "metadata": {
        "volume_ratio": 2.246729419892057,
        "interpretation": "increased_interest"
      }
    },
    {
      "signal_type": "volume_anomaly",
      "symbol": "MSFT",
      "timestamp": "2025-09-16T22:29:42.906119",
      "strength": 0.8896502600105249,
      "confidence": 1.0,
      "description": "Volume anomaly detected: 4.26\u03c3 deviation",
      "metadata": {
        "zscore": 4.260738400277628,
        "current_volume": 139863312,
        "mean_volume": 58167152.94736842
      }
    },
    {
      "signal_type": "high_volume",
      "symbol": "MSFT",
      "timestamp": "2025-09-16T22:29:42.906144",
      "strength": 0.553466389358483,
      "confidence": 0.4155764732973523,
      "description": "High volume: 2.25x average",
      "metadata": {
        "volume_ratio": 2.246729419892057,
        "interpretation": "increased_interest"
      }
    },
    {
      "signal_type": "volume_anomaly",
      "symbol": "MSFT",
      "timestamp": "2025-09-16T22:29:42.908948",
      "strength": 0.8896502600105249,
      "confidence": 1.0,
      "description": "Volume anomaly detected: 4.26\u03c3 deviation",
      "metadata": {
        "zscore": 4.260738400277628,
        "current_volume": 139863312,
        "mean_volume": 58167152.94736842
      }
    },
    {
      "signal_type": "high_volume",
      "symbol": "MSFT",
      "timestamp": "2025-09-16T22:29:42.908968",
      "strength": 0.553466389358483,
      "confidence": 0.4155764732973523,
      "description": "High volume: 2.25x average",
      "metadata": {
        "volume_ratio": 2.246729419892057,
        "interpretation": "increased_interest"
      }
    },
    {
      "signal_type": "volume_anomaly",
      "symbol": "MSFT",
      "timestamp": "2025-09-16T22:29:42.911748",
      "strength": 0.8896502600105249,
      "confidence": 1.0,
      "description": "Volume anomaly detected: 4.26\u03c3 deviation",
      "metadata": {
        "zscore": 4.260738400277628,
        "current_volume": 139863312,
        "mean_volume": 58167152.94736842
      }
    },
    {
      "signal_type": "high_volume",
      "symbol": "MSFT",
      "timestamp": "2025-09-16T22:29:42.911768",
      "strength": 0.553466389358483,
      "confidence": 0.4155764732973523,
      "description": "High volume: 2.25x average",
      "metadata": {
        "volume_ratio": 2.246729419892057,
        "interpretation": "increased_interest"
      }
    },
    {
      "signal_type": "volume_anomaly",
      "symbol": "MSFT",
      "timestamp": "2025-09-16T22:29:42.914502",
      "strength": 0.8896502600105249,
      "confidence": 1.0,
      "description": "Volume anomaly detected: 4.26\u03c3 deviation",
      "metadata": {
        "zscore": 4.260738400277628,
        "current_volume": 139863312,
        "mean_volume": 58167152.94736842
      }
    },
    {
      "signal_type": "high_volume",
      "symbol": "MSFT",
      "timestamp": "2025-09-16T22:29:42.914520",
      "strength": 0.553466389358483,
      "confidence": 0.4155764732973523,
      "description": "High volume: 2.25x average",
      "metadata": {
        "volume_ratio": 2.246729419892057,
        "interpretation": "increased_interest"
      }
    },
    {
      "signal_type": "volume_anomaly",
      "symbol": "MSFT",
      "timestamp": "2025-09-16T22:29:42.917193",
      "strength": 0.8896502600105249,
      "confidence": 1.0,
      "description": "Volume anomaly detected: 4.26\u03c3 deviation",
      "metadata": {
        "zscore": 4.260738400277628,
        "current_volume": 139863312,
        "mean_volume": 58167152.94736842
      }
    },
    {
      "signal_type": "high_volume",
      "symbol": "MSFT",
      "timestamp": "2025-09-16T22:29:42.917211",
      "strength": 0.553466389358483,
      "confidence": 0.4155764732973523,
      "description": "High volume: 2.25x average",
      "metadata": {
        "volume_ratio": 2.246729419892057,
        "interpretation": "increased_interest"
      }
    },
    {
      "signal_type": "volume_anomaly",
      "symbol": "MSFT",
      "timestamp": "2025-09-16T22:29:42.919873",
      "strength": 0.8896502600105249,
      "confidence": 1.0,
      "description": "Volume anomaly detected: 4.26\u03c3 deviation",
      "metadata": {
        "zscore": 4.260738400277628,
        "current_volume": 139863312,
        "mean_volume": 58167152.94736842
      }
    },
    {
      "signal_type": "high_volume",
      "symbol": "MSFT",
      "timestamp": "2025-09-16T22:29:42.919891",
      "strength": 0.553466389358483,
      "confidence": 0.4155764732973523,
      "description": "High volume: 2.25x average",
      "metadata": {
        "volume_ratio": 2.246729419892057,
        "interpretation": "increased_interest"
      }
    },
    {
      "signal_type": "volume_anomaly",
      "symbol": "MSFT",
      "timestamp": "2025-09-16T22:29:42.922573",
      "strength": 0.8896502600105249,
      "confidence": 1.0,
      "description": "Volume anomaly detected: 4.26\u03c3 deviation",
      "metadata": {
        "zscore": 4.260738400277628,
        "current_volume": 139863312,
        "mean_volume": 58167152.94736842
      }
    },
    {
      "signal_type": "high_volume",
      "symbol": "MSFT",
      "timestamp": "2025-09-16T22:29:42.922591",
      "strength": 0.553466389358483,
      "confidence": 0.4155764732973523,
      "description": "High volume: 2.25x average",
      "metadata": {
        "volume_ratio": 2.246729419892057,
        "interpretation": "increased_interest"
      }
    },
    {
      "signal_type": "volume_anomaly",
      "symbol": "MSFT",
      "timestamp": "2025-09-16T22:29:42.925587",
      "strength": 0.8896502600105249,
      "confidence": 1.0,
      "description": "Volume anomaly detected: 4.26\u03c3 deviation",
      "metadata": {
        "zscore": 4.260738400277628,
        "current_volume": 139863312,
        "mean_volume": 58167152.94736842
      }
    },
    {
      "signal_type": "high_volume",
      "symbol": "MSFT",
      "timestamp": "2025-09-16T22:29:42.925610",
      "strength": 0.553466389358483,
      "confidence": 0.4155764732973523,
      "description": "High volume: 2.25x average",
      "metadata": {
        "volume_ratio": 2.246729419892057,
        "interpretation": "increased_interest"
      }
    },
    {
      "signal_type": "volume_anomaly",
      "symbol": "MSFT",
      "timestamp": "2025-09-16T22:29:42.928410",
      "strength": 0.8896502600105249,
      "confidence": 1.0,
      "description": "Volume anomaly detected: 4.26\u03c3 deviation",
      "metadata": {
        "zscore": 4.260738400277628,
        "current_volume": 139863312,
        "mean_volume": 58167152.94736842
      }
    },
    {
      "signal_type": "high_volume",
      "symbol": "MSFT",
      "timestamp": "2025-09-16T22:29:42.928430",
      "strength": 0.553466389358483,
      "confidence": 0.4155764732973523,
      "description": "High volume: 2.25x average",
      "metadata": {
        "volume_ratio": 2.246729419892057,
        "interpretation": "increased_interest"
      }
    },
    {
      "signal_type": "volume_anomaly",
      "symbol": "MSFT",
      "timestamp": "2025-09-16T22:29:42.931828",
      "strength": 0.8896502600105249,
      "confidence": 1.0,
      "description": "Volume anomaly detected: 4.26\u03c3 deviation",
      "metadata": {
        "zscore": 4.260738400277628,
        "current_volume": 139863312,
        "mean_volume": 58167152.94736842
      }
    },
    {
      "signal_type": "high_volume",
      "symbol": "MSFT",
      "timestamp": "2025-09-16T22:29:42.931853",
      "strength": 0.553466389358483,
      "confidence": 0.4155764732973523,
      "description": "High volume: 2.25x average",
      "metadata": {
        "volume_ratio": 2.246729419892057,
        "interpretation": "increased_interest"
      }
    },
    {
      "signal_type": "volume_anomaly",
      "symbol": "MSFT",
      "timestamp": "2025-09-16T22:29:42.934949",
      "strength": 0.8896502600105249,
      "confidence": 1.0,
      "description": "Volume anomaly detected: 4.26\u03c3 deviation",
      "metadata": {
        "zscore": 4.260738400277628,
        "current_volume": 139863312,
        "mean_volume": 58167152.94736842
      }
    },
    {
      "signal_type": "high_volume",
      "symbol": "MSFT",
      "timestamp": "2025-09-16T22:29:42.934972",
      "strength": 0.553466389358483,
      "confidence": 0.4155764732973523,
      "description": "High volume: 2.25x average",
      "metadata": {
        "volume_ratio": 2.246729419892057,
        "interpretation": "increased_interest"
      }
    },
    {
      "signal_type": "volume_anomaly",
      "symbol": "XOM",
      "timestamp": "2025-09-16T22:29:46.034765",
      "strength": 0.7061086803618462,
      "confidence": 0.6595351473391124,
      "description": "Volume anomaly detected: 2.64\u03c3 deviation",
      "metadata": {
        "zscore": 2.63814058935645,
        "current_volume": 72566037,
        "mean_volume": 40506788.578947365
      }
    },
    {
      "signal_type": "rsi_overbought",
      "symbol": "AAPL",
      "timestamp": "2025-09-16T22:29:47.037116",
      "strength": -0.8,
      "confidence": 1.0,
      "description": "RSI overbought: 100.0",
      "metadata": {
        "rsi": 100.0
      }
    },
    {
      "signal_type": "rsi_overbought",
      "symbol": "GOOGL",
      "timestamp": "2025-09-16T22:29:47.037529",
      "strength": -0.8,
      "confidence": 1.0,
      "description": "RSI overbought: 100.0",
      "metadata": {
        "rsi": 100.0
      }
    },
    {
      "signal_type": "rsi_overbought",
      "symbol": "MSFT",
      "timestamp": "2025-09-16T22:29:47.037712",
      "strength": -0.8,
      "confidence": 1.0,
      "description": "RSI overbought: 100.0",
      "metadata": {
        "rsi": 100.0
      }
    },
    {
      "signal_type": "rsi_overbought",
      "symbol": "AMZN",
      "timestamp": "2025-09-16T22:29:47.037867",
      "strength": -0.8,
      "confidence": 1.0,
      "description": "RSI overbought: 100.0",
      "metadata": {
        "rsi": 100.0
      }
    },
    {
      "signal_type": "rsi_overbought",
      "symbol": "TSLA",
      "timestamp": "2025-09-16T22:29:47.038042",
      "strength": -0.8,
      "confidence": 1.0,
      "description": "RSI overbought: 100.0",
      "metadata": {
        "rsi": 100.0
      }
    },
    {
      "signal_type": "rsi_overbought",
      "symbol": "NVDA",
      "timestamp": "2025-09-16T22:29:47.038246",
      "strength": -0.8,
      "confidence": 1.0,
      "description": "RSI overbought: 100.0",
      "metadata": {
        "rsi": 100.0
      }
    },
    {
      "signal_type": "rsi_overbought",
      "symbol": "META",
      "timestamp": "2025-09-16T22:29:47.038405",
      "strength": -0.8,
      "confidence": 1.0,
      "description": "RSI overbought: 100.0",
      "metadata": {
        "rsi": 100.0
      }
    },
    {
      "signal_type": "rsi_overbought",
      "symbol": "NFLX",
      "timestamp": "2025-09-16T22:29:47.038553",
      "strength": -0.8,
      "confidence": 1.0,
      "description": "RSI overbought: 100.0",
      "metadata": {
        "rsi": 100.0
      }
    },
    {
      "signal_type": "rsi_overbought",
      "symbol": "JPM",
      "timestamp": "2025-09-16T22:29:47.038695",
      "strength": -0.8,
      "confidence": 1.0,
      "description": "RSI overbought: 100.0",
      "metadata": {
        "rsi": 100.0
      }
    },
    {
      "signal_type": "rsi_overbought",
      "symbol": "BAC",
      "timestamp": "2025-09-16T22:29:47.038928",
      "strength": -0.8,
      "confidence": 1.0,
      "description": "RSI overbought: 100.0",
      "metadata": {
        "rsi": 100.0
      }
    },
    {
      "signal_type": "rsi_overbought",
      "symbol": "JNJ",
      "timestamp": "2025-09-16T22:29:47.039294",
      "strength": -0.8,
      "confidence": 1.0,
      "description": "RSI overbought: 100.0",
      "metadata": {
        "rsi": 100.0
      }
    },
    {
      "signal_type": "rsi_overbought",
      "symbol": "PFE",
      "timestamp": "2025-09-16T22:29:47.039461",
      "strength": -0.8,
      "confidence": 1.0,
      "description": "RSI overbought: 100.0",
      "metadata": {
        "rsi": 100.0
      }
    },
    {
      "signal_type": "rsi_overbought",
      "symbol": "XOM",
      "timestamp": "2025-09-16T22:29:47.039608",
      "strength": -0.8,
      "confidence": 1.0,
      "description": "RSI overbought: 100.0",
      "metadata": {
        "rsi": 100.0
      }
    },
    {
      "signal_type": "rsi_overbought",
      "symbol": "CVX",
      "timestamp": "2025-09-16T22:29:47.039750",
      "strength": -0.8,
      "confidence": 1.0,
      "description": "RSI overbought: 100.0",
      "metadata": {
        "rsi": 100.0
      }
    },
    {
      "signal_type": "rsi_overbought",
      "symbol": "WMT",
      "timestamp": "2025-09-16T22:29:47.039889",
      "strength": -0.8,
      "confidence": 1.0,
      "description": "RSI overbought: 100.0",
      "metadata": {
        "rsi": 100.0
      }
    },
    {
      "signal_type": "rsi_overbought",
      "symbol": "HD",
      "timestamp": "2025-09-16T22:29:47.040022",
      "strength": -0.8,
      "confidence": 1.0,
      "description": "RSI overbought: 100.0",
      "metadata": {
        "rsi": 100.0
      }
    },
    {
      "signal_type": "rsi_overbought",
      "symbol": "PG",
      "timestamp": "2025-09-16T22:29:47.040155",
      "strength": -0.8,
      "confidence": 1.0,
      "description": "RSI overbought: 100.0",
      "metadata": {
        "rsi": 100.0
      }
    },
    {
      "signal_type": "rsi_overbought",
      "symbol": "KO",
      "timestamp": "2025-09-16T22:29:47.040287",
      "strength": -0.8,
      "confidence": 1.0,
      "description": "RSI overbought: 100.0",
      "metadata": {
        "rsi": 100.0
      }
    },
    {
      "signal_type": "rsi_overbought",
      "symbol": "DIS",
      "timestamp": "2025-09-16T22:29:47.040500",
      "strength": -0.8,
      "confidence": 1.0,
      "description": "RSI overbought: 100.0",
      "metadata": {
        "rsi": 100.0
      }
    },
    {
      "signal_type": "rsi_overbought",
      "symbol": "V",
      "timestamp": "2025-09-16T22:29:47.040664",
      "strength": -0.8,
      "confidence": 1.0,
      "description": "RSI overbought: 100.0",
      "metadata": {
        "rsi": 100.0
      }
    },
    {
      "signal_type": "volume_anomaly",
      "symbol": "GOOGL",
      "timestamp": "2025-09-16T22:29:48.045418",
      "strength": 0.6824265995828046,
      "confidence": 0.6252312977743159,
      "description": "Volume anomaly detected: 2.50\u03c3 deviation",
      "metadata": {
        "zscore": 2.5009251910972634,
        "current_volume": 88003082,
        "mean_volume": 47689087.526315786
      }
    },
    {
      "signal_type": "volume_anomaly",
      "symbol": "PG",
      "timestamp": "2025-09-16T22:29:48.048223",
      "strength": 0.695731431022694,
      "confidence": 0.6442345078072356,
      "description": "Volume anomaly detected: 2.58\u03c3 deviation",
      "metadata": {
        "zscore": 2.5769380312289423,
        "current_volume": 28850287,
        "mean_volume": 16407846.368421054
      }
    },
    {
      "signal_type": "volume_anomaly",
      "symbol": "AAPL",
      "timestamp": "2025-09-16T22:29:49.070378",
      "strength": 0.7138067988018828,
      "confidence": 0.6711769732129161,
      "description": "Volume anomaly detected: 2.68\u03c3 deviation",
      "metadata": {
        "zscore": 2.6847078928516646,
        "current_volume": 293481165,
        "mean_volume": 161164879.89473686
      }
    },
    {
      "signal_type": "volume_anomaly",
      "symbol": "AAPL",
      "timestamp": "2025-09-16T22:29:49.073547",
      "strength": 0.7138067988018828,
      "confidence": 0.6711769732129161,
      "description": "Volume anomaly detected: 2.68\u03c3 deviation",
      "metadata": {
        "zscore": 2.6847078928516646,
        "current_volume": 293481165,
        "mean_volume": 161164879.89473686
      }
    },
    {
      "signal_type": "volume_anomaly",
      "symbol": "AAPL",
      "timestamp": "2025-09-16T22:29:49.077003",
      "strength": 0.7138067988018828,
      "confidence": 0.6711769732129161,
      "description": "Volume anomaly detected: 2.68\u03c3 deviation",
      "metadata": {
        "zscore": 2.6847078928516646,
        "current_volume": 293481165,
        "mean_volume": 161164879.89473686
      }
    },
    {
      "signal_type": "volume_anomaly",
      "symbol": "AAPL",
      "timestamp": "2025-09-16T22:29:49.080108",
      "strength": 0.7138067988018828,
      "confidence": 0.6711769732129161,
      "description": "Volume anomaly detected: 2.68\u03c3 deviation",
      "metadata": {
        "zscore": 2.6847078928516646,
        "current_volume": 293481165,
        "mean_volume": 161164879.89473686
      }
    },
    {
      "signal_type": "volume_anomaly",
      "symbol": "AAPL",
      "timestamp": "2025-09-16T22:29:49.083332",
      "strength": 0.7138067988018828,
      "confidence": 0.6711769732129161,
      "description": "Volume anomaly detected: 2.68\u03c3 deviation",
      "metadata": {
        "zscore": 2.6847078928516646,
        "current_volume": 293481165,
        "mean_volume": 161164879.89473686
      }
    },
    {
      "signal_type": "volume_anomaly",
      "symbol": "AAPL",
      "timestamp": "2025-09-16T22:29:49.086631",
      "strength": 0.7138067988018828,
      "confidence": 0.6711769732129161,
      "description": "Volume anomaly detected: 2.68\u03c3 deviation",
      "metadata": {
        "zscore": 2.6847078928516646,
        "current_volume": 293481165,
        "mean_volume": 161164879.89473686
      }
    },
    {
      "signal_type": "volume_anomaly",
      "symbol": "AAPL",
      "timestamp": "2025-09-16T22:29:49.089495",
      "strength": 0.7138067988018828,
      "confidence": 0.6711769732129161,
      "description": "Volume anomaly detected: 2.68\u03c3 deviation",
      "metadata": {
        "zscore": 2.6847078928516646,
        "current_volume": 293481165,
        "mean_volume": 161164879.89473686
      }
    },
    {
      "signal_type": "volume_anomaly",
      "symbol": "AAPL",
      "timestamp": "2025-09-16T22:29:49.092586",
      "strength": 0.7138067988018828,
      "confidence": 0.6711769732129161,
      "description": "Volume anomaly detected: 2.68\u03c3 deviation",
      "metadata": {
        "zscore": 2.6847078928516646,
        "current_volume": 293481165,
        "mean_volume": 161164879.89473686
      }
    },
    {
      "signal_type": "volume_anomaly",
      "symbol": "AAPL",
      "timestamp": "2025-09-16T22:29:49.095649",
      "strength": 0.7138067988018828,
      "confidence": 0.6711769732129161,
      "description": "Volume anomaly detected: 2.68\u03c3 deviation",
      "metadata": {
        "zscore": 2.6847078928516646,
        "current_volume": 293481165,
        "mean_volume": 161164879.89473686
      }
    },
    {
      "signal_type": "volume_anomaly",
      "symbol": "AAPL",
      "timestamp": "2025-09-16T22:29:49.098672",
      "strength": 0.7138067988018828,
      "confidence": 0.6711769732129161,
      "description": "Volume anomaly detected: 2.68\u03c3 deviation",
      "metadata": {
        "zscore": 2.6847078928516646,
        "current_volume": 293481165,
        "mean_volume": 161164879.89473686
      }
    },
    {
      "signal_type": "volume_anomaly",
      "symbol": "AAPL",
      "timestamp": "2025-09-16T22:29:49.101965",
      "strength": 0.7138067988018828,
      "confidence": 0.6711769732129161,
      "description": "Volume anomaly detected: 2.68\u03c3 deviation",
      "metadata": {
        "zscore": 2.6847078928516646,
        "current_volume": 293481165,
        "mean_volume": 161164879.89473686
      }
    },
    {
      "signal_type": "volume_anomaly",
      "symbol": "AAPL",
      "timestamp": "2025-09-16T22:29:49.104817",
      "strength": 0.7138067988018828,
      "confidence": 0.6711769732129161,
      "description": "Volume anomaly detected: 2.68\u03c3 deviation",
      "metadata": {
        "zscore": 2.6847078928516646,
        "current_volume": 293481165,
        "mean_volume": 161164879.89473686
      }
    },
    {
      "signal_type": "volume_anomaly",
      "symbol": "AAPL",
      "timestamp": "2025-09-16T22:29:49.108151",
      "strength": 0.7138067988018828,
      "confidence": 0.6711769732129161,
      "description": "Volume anomaly detected: 2.68\u03c3 deviation",
      "metadata": {
        "zscore": 2.6847078928516646,
        "current_volume": 293481165,
        "mean_volume": 161164879.89473686
      }
    },
    {
      "signal_type": "volume_anomaly",
      "symbol": "AAPL",
      "timestamp": "2025-09-16T22:29:49.112609",
      "strength": 0.7138067988018828,
      "confidence": 0.6711769732129161,
      "description": "Volume anomaly detected: 2.68\u03c3 deviation",
      "metadata": {
        "zscore": 2.6847078928516646,
        "current_volume": 293481165,
        "mean_volume": 161164879.89473686
      }
    },
    {
      "signal_type": "volume_anomaly",
      "symbol": "AAPL",
      "timestamp": "2025-09-16T22:29:49.115996",
      "strength": 0.7138067988018828,
      "confidence": 0.6711769732129161,
      "description": "Volume anomaly detected: 2.68\u03c3 deviation",
      "metadata": {
        "zscore": 2.6847078928516646,
        "current_volume": 293481165,
        "mean_volume": 161164879.89473686
      }
    },
    {
      "signal_type": "volume_anomaly",
      "symbol": "AAPL",
      "timestamp": "2025-09-16T22:29:49.119726",
      "strength": 0.7138067988018828,
      "confidence": 0.6711769732129161,
      "description": "Volume anomaly detected: 2.68\u03c3 deviation",
      "metadata": {
        "zscore": 2.6847078928516646,
        "current_volume": 293481165,
        "mean_volume": 161164879.89473686
      }
    },
    {
      "signal_type": "volume_anomaly",
      "symbol": "AAPL",
      "timestamp": "2025-09-16T22:29:49.122564",
      "strength": 0.7138067988018828,
      "confidence": 0.6711769732129161,
      "description": "Volume anomaly detected: 2.68\u03c3 deviation",
      "metadata": {
        "zscore": 2.6847078928516646,
        "current_volume": 293481165,
        "mean_volume": 161164879.89473686
      }
    },
    {
      "signal_type": "volume_anomaly",
      "symbol": "AAPL",
      "timestamp": "2025-09-16T22:29:49.126320",
      "strength": 0.7138067988018828,
      "confidence": 0.6711769732129161,
      "description": "Volume anomaly detected: 2.68\u03c3 deviation",
      "metadata": {
        "zscore": 2.6847078928516646,
        "current_volume": 293481165,
        "mean_volume": 161164879.89473686
      }
    },
    {
      "signal_type": "volume_anomaly",
      "symbol": "AAPL",
      "timestamp": "2025-09-16T22:29:49.129330",
      "strength": 0.7138067988018828,
      "confidence": 0.6711769732129161,
      "description": "Volume anomaly detected: 2.68\u03c3 deviation",
      "metadata": {
        "zscore": 2.6847078928516646,
        "current_volume": 293481165,
        "mean_volume": 161164879.89473686
      }
    },
    {
      "signal_type": "volume_anomaly",
      "symbol": "AAPL",
      "timestamp": "2025-09-16T22:29:49.133685",
      "strength": 0.7138067988018828,
      "confidence": 0.6711769732129161,
      "description": "Volume anomaly detected: 2.68\u03c3 deviation",
      "metadata": {
        "zscore": 2.6847078928516646,
        "current_volume": 293481165,
        "mean_volume": 161164879.89473686
      }
    },
    {
      "signal_type": "volume_anomaly",
      "symbol": "AAPL",
      "timestamp": "2025-09-16T22:29:49.136860",
      "strength": 0.7138067988018828,
      "confidence": 0.6711769732129161,
      "description": "Volume anomaly detected: 2.68\u03c3 deviation",
      "metadata": {
        "zscore": 2.6847078928516646,
        "current_volume": 293481165,
        "mean_volume": 161164879.89473686
      }
    },
    {
      "signal_type": "rsi_overbought",
      "symbol": "AAPL",
      "timestamp": "2025-09-16T22:29:52.403991",
      "strength": -0.8,
      "confidence": 1.0,
      "description": "RSI overbought: 100.0",
      "metadata": {
        "rsi": 100.0
      }
    },
    {
      "signal_type": "rsi_overbought",
      "symbol": "GOOGL",
      "timestamp": "2025-09-16T22:29:52.404209",
      "strength": -0.8,
      "confidence": 1.0,
      "description": "RSI overbought: 100.0",
      "metadata": {
        "rsi": 100.0
      }
    },
    {
      "signal_type": "rsi_overbought",
      "symbol": "MSFT",
      "timestamp": "2025-09-16T22:29:52.404360",
      "strength": -0.8,
      "confidence": 1.0,
      "description": "RSI overbought: 100.0",
      "metadata": {
        "rsi": 100.0
      }
    },
    {
      "signal_type": "rsi_overbought",
      "symbol": "AMZN",
      "timestamp": "2025-09-16T22:29:52.404500",
      "strength": -0.8,
      "confidence": 1.0,
      "description": "RSI overbought: 100.0",
      "metadata": {
        "rsi": 100.0
      }
    },
    {
      "signal_type": "rsi_overbought",
      "symbol": "TSLA",
      "timestamp": "2025-09-16T22:29:52.404634",
      "strength": -0.8,
      "confidence": 1.0,
      "description": "RSI overbought: 100.0",
      "metadata": {
        "rsi": 100.0
      }
    },
    {
      "signal_type": "rsi_overbought",
      "symbol": "NVDA",
      "timestamp": "2025-09-16T22:29:52.404772",
      "strength": -0.8,
      "confidence": 1.0,
      "description": "RSI overbought: 100.0",
      "metadata": {
        "rsi": 100.0
      }
    },
    {
      "signal_type": "rsi_overbought",
      "symbol": "META",
      "timestamp": "2025-09-16T22:29:52.404902",
      "strength": -0.8,
      "confidence": 1.0,
      "description": "RSI overbought: 100.0",
      "metadata": {
        "rsi": 100.0
      }
    },
    {
      "signal_type": "rsi_overbought",
      "symbol": "NFLX",
      "timestamp": "2025-09-16T22:29:52.405030",
      "strength": -0.8,
      "confidence": 1.0,
      "description": "RSI overbought: 100.0",
      "metadata": {
        "rsi": 100.0
      }
    },
    {
      "signal_type": "rsi_overbought",
      "symbol": "JPM",
      "timestamp": "2025-09-16T22:29:52.405156",
      "strength": -0.8,
      "confidence": 1.0,
      "description": "RSI overbought: 100.0",
      "metadata": {
        "rsi": 100.0
      }
    },
    {
      "signal_type": "rsi_overbought",
      "symbol": "BAC",
      "timestamp": "2025-09-16T22:29:52.405281",
      "strength": -0.8,
      "confidence": 1.0,
      "description": "RSI overbought: 100.0",
      "metadata": {
        "rsi": 100.0
      }
    },
    {
      "signal_type": "rsi_overbought",
      "symbol": "JNJ",
      "timestamp": "2025-09-16T22:29:52.405406",
      "strength": -0.8,
      "confidence": 1.0,
      "description": "RSI overbought: 100.0",
      "metadata": {
        "rsi": 100.0
      }
    },
    {
      "signal_type": "rsi_overbought",
      "symbol": "PFE",
      "timestamp": "2025-09-16T22:29:52.405530",
      "strength": -0.8,
      "confidence": 1.0,
      "description": "RSI overbought: 100.0",
      "metadata": {
        "rsi": 100.0
      }
    },
    {
      "signal_type": "rsi_overbought",
      "symbol": "XOM",
      "timestamp": "2025-09-16T22:29:52.405653",
      "strength": -0.8,
      "confidence": 1.0,
      "description": "RSI overbought: 100.0",
      "metadata": {
        "rsi": 100.0
      }
    },
    {
      "signal_type": "rsi_overbought",
      "symbol": "CVX",
      "timestamp": "2025-09-16T22:29:52.405776",
      "strength": -0.8,
      "confidence": 1.0,
      "description": "RSI overbought: 100.0",
      "metadata": {
        "rsi": 100.0
      }
    },
    {
      "signal_type": "rsi_overbought",
      "symbol": "WMT",
      "timestamp": "2025-09-16T22:29:52.405898",
      "strength": -0.8,
      "confidence": 1.0,
      "description": "RSI overbought: 100.0",
      "metadata": {
        "rsi": 100.0
      }
    },
    {
      "signal_type": "rsi_overbought",
      "symbol": "HD",
      "timestamp": "2025-09-16T22:29:52.406021",
      "strength": -0.8,
      "confidence": 1.0,
      "description": "RSI overbought: 100.0",
      "metadata": {
        "rsi": 100.0
      }
    },
    {
      "signal_type": "rsi_overbought",
      "symbol": "PG",
      "timestamp": "2025-09-16T22:29:52.406144",
      "strength": -0.8,
      "confidence": 1.0,
      "description": "RSI overbought: 100.0",
      "metadata": {
        "rsi": 100.0
      }
    },
    {
      "signal_type": "rsi_overbought",
      "symbol": "KO",
      "timestamp": "2025-09-16T22:29:52.406268",
      "strength": -0.8,
      "confidence": 1.0,
      "description": "RSI overbought: 100.0",
      "metadata": {
        "rsi": 100.0
      }
    },
    {
      "signal_type": "rsi_overbought",
      "symbol": "DIS",
      "timestamp": "2025-09-16T22:29:52.406390",
      "strength": -0.8,
      "confidence": 1.0,
      "description": "RSI overbought: 100.0",
      "metadata": {
        "rsi": 100.0
      }
    },
    {
      "signal_type": "rsi_overbought",
      "symbol": "V",
      "timestamp": "2025-09-16T22:29:52.406512",
      "strength": -0.8,
      "confidence": 1.0,
      "description": "RSI overbought: 100.0",
      "metadata": {
        "rsi": 100.0
      }
    },
    {
      "signal_type": "volume_anomaly",
      "symbol": "JPM",
      "timestamp": "2025-09-16T22:29:53.411384",
      "strength": 0.81106856831789,
      "confidence": 0.8476080620235646,
      "description": "Volume anomaly detected: 3.39\u03c3 deviation",
      "metadata": {
        "zscore": 3.3904322480942586,
        "current_volume": 62333956,
        "mean_volume": 29017295.63157895
      }
    },
    {
      "signal_type": "high_volume",
      "symbol": "JPM",
      "timestamp": "2025-09-16T22:29:53.411415",
      "strength": 0.4744281002644473,
      "confidence": 0.3438461541415639,
      "description": "High volume: 2.03x average",
      "metadata": {
        "volume_ratio": 2.0315384624246917,
        "interpretation": "increased_interest"
      }
    },
    {
      "signal_type": "volume_anomaly",
      "symbol": "WMT",
      "timestamp": "2025-09-16T22:29:54.416614",
      "strength": 0.8811065801454465,
      "confidence": 1.0,
      "description": "Volume anomaly detected: 4.14\u03c3 deviation",
      "metadata": {
        "zscore": 4.1420820432057335,
        "current_volume": 57843678,
        "mean_volume": 25377175.263157893
      }
    },
    {
      "signal_type": "high_volume",
      "symbol": "WMT",
      "timestamp": "2025-09-16T22:29:54.416648",
      "strength": 0.5162102161575329,
      "confidence": 0.3807729133790425,
      "description": "High volume: 2.14x average",
      "metadata": {
        "volume_ratio": 2.1423187401371275,
        "interpretation": "increased_interest"
      }
    },
    {
      "signal_type": "volume_anomaly",
      "symbol": "CVX",
      "timestamp": "2025-09-16T22:29:55.420349",
      "strength": 0.9619851542133621,
      "confidence": 1.0,
      "description": "Volume anomaly detected: 5.92\u03c3 deviation",
      "metadata": {
        "zscore": 5.915602967114573,
        "current_volume": 55067579,
        "mean_volume": 21476432.57894737
      }
    },
    {
      "signal_type": "high_volume",
      "symbol": "CVX",
      "timestamp": "2025-09-16T22:29:55.420379",
      "strength": 0.5973757929762531,
      "confidence": 0.4593712647398706,
      "description": "High volume: 2.38x average",
      "metadata": {
        "volume_ratio": 2.3781137942196118,
        "interpretation": "increased_interest"
      }
    },
    {
      "signal_type": "volume_anomaly",
      "symbol": "V",
      "timestamp": "2025-09-16T22:29:55.421188",
      "strength": 0.80947811121637,
      "confidence": 0.8441349962328808,
      "description": "Volume anomaly detected: 3.38\u03c3 deviation",
      "metadata": {
        "zscore": 3.376539984931523,
        "current_volume": 30821442,
        "mean_volume": 14728693.47368421
      }
    },
    {
      "signal_type": "volume_anomaly",
      "symbol": "JNJ",
      "timestamp": "2025-09-16T22:29:57.427677",
      "strength": 0.7363773524221123,
      "confidence": 0.7068890719169149,
      "description": "Volume anomaly detected: 2.83\u03c3 deviation",
      "metadata": {
        "zscore": 2.8275562876676594,
        "current_volume": 37362192,
        "mean_volume": 21905955.94736842
      }
    },
    {
      "signal_type": "volume_anomaly",
      "symbol": "BAC",
      "timestamp": "2025-09-16T22:29:59.558378",
      "strength": 0.8182631296739344,
      "confidence": 0.8636539224566366,
      "description": "Volume anomaly detected: 3.45\u03c3 deviation",
      "metadata": {
        "zscore": 3.4546156898265465,
        "current_volume": 167392821,
        "mean_volume": 84096982.4736842
      }
    },
    {
      "signal_type": "volume_anomaly",
      "symbol": "PFE",
      "timestamp": "2025-09-16T22:29:59.558686",
      "strength": 0.7370311501842853,
      "confidence": 0.7079614185026062,
      "description": "Volume anomaly detected: 2.83\u03c3 deviation",
      "metadata": {
        "zscore": 2.8318456740104248,
        "current_volume": 118157151,
        "mean_volume": 64600729.578947365
      }
    },
    {
      "signal_type": "volume_anomaly",
      "symbol": "AAPL",
      "timestamp": "2025-09-16T22:30:00.560718",
      "strength": 0.7461611723890093,
      "confidence": 0.7231783173713582,
      "description": "Volume anomaly detected: 2.89\u03c3 deviation",
      "metadata": {
        "zscore": 2.8927132694854327,
        "current_volume": 272006288,
        "mean_volume": 138066673.68421054
      }
    },
    {
      "signal_type": "volume_anomaly",
      "symbol": "V",
      "timestamp": "2025-09-16T22:30:00.564163",
      "strength": 0.8059232900215628,
      "confidence": 0.8364651618132133,
      "description": "Volume anomaly detected: 3.35\u03c3 deviation",
      "metadata": {
        "zscore": 3.345860647252853,
        "current_volume": 31229920,
        "mean_volume": 15455293.157894736
      }
    },
    {
      "signal_type": "volume_anomaly",
      "symbol": "MSFT",
      "timestamp": "2025-09-16T22:30:02.569631",
      "strength": 0.6898517447902437,
      "confidence": 0.6357546199961673,
      "description": "Volume anomaly detected: 2.54\u03c3 deviation",
      "metadata": {
        "zscore": 2.5430184799846693,
        "current_volume": 98936949,
        "mean_volume": 61852754.2631579
      }
    },
    {
      "signal_type": "volume_anomaly",
      "symbol": "JNJ",
      "timestamp": "2025-09-16T22:30:03.575849",
      "strength": 0.803251536914083,
      "confidence": 0.8307827429722894,
      "description": "Volume anomaly detected: 3.32\u03c3 deviation",
      "metadata": {
        "zscore": 3.3231309718891575,
        "current_volume": 43338913,
        "mean_volume": 23254482.263157893
      }
    },
    {
      "signal_type": "volume_anomaly",
      "symbol": "WMT",
      "timestamp": "2025-09-16T22:30:03.576525",
      "strength": 0.7815351468073753,
      "confidence": 0.7869770876174539,
      "description": "Volume anomaly detected: 3.15\u03c3 deviation",
      "metadata": {
        "zscore": 3.1479083504698155,
        "current_volume": 59345897,
        "mean_volume": 27302293.05263158
      }
    },
    {
      "signal_type": "high_volume",
      "symbol": "WMT",
      "timestamp": "2025-09-16T22:30:03.576549",
      "strength": 0.4827676449723541,
      "confidence": 0.3510578159385762,
      "description": "High volume: 2.05x average",
      "metadata": {
        "volume_ratio": 2.0531734478157286,
        "interpretation": "increased_interest"
      }
    },
    {
      "signal_type": "volume_anomaly",
      "symbol": "DIS",
      "timestamp": "2025-09-16T22:30:04.581386",
      "strength": 0.7607333741332843,
      "confidence": 0.7484651893368742,
      "description": "Volume anomaly detected: 2.99\u03c3 deviation",
      "metadata": {
        "zscore": 2.993860757347497,
        "current_volume": 35501011,
        "mean_volume": 20819179.36842105
      }
    },
    {
      "signal_type": "volume_anomaly",
      "symbol": "KO",
      "timestamp": "2025-09-16T22:30:07.593961",
      "strength": 0.687064829947166,
      "confidence": 0.631781049857018,
      "description": "Volume anomaly detected: 2.53\u03c3 deviation",
      "metadata": {
        "zscore": 2.527124199428072,
        "current_volume": 63096054,
        "mean_volume": 33971280.421052635
      }
    },
    {
      "signal_type": "volume_anomaly",
      "symbol": "CVX",
      "timestamp": "2025-09-16T22:30:08.598866",
      "strength": 0.7464876700968788,
      "confidence": 0.7237310789714915,
      "description": "Volume anomaly detected: 2.89\u03c3 deviation",
      "metadata": {
        "zscore": 2.894924315885966,
        "current_volume": 40885046,
        "mean_volume": 22110386.47368421
      }
    },
    {
      "signal_type": "rsi_overbought",
      "symbol": "AAPL",
      "timestamp": "2025-09-16T22:30:09.600153",
      "strength": -0.8,
      "confidence": 1.0,
      "description": "RSI overbought: 100.0",
      "metadata": {
        "rsi": 100.0
      }
    },
    {
      "signal_type": "rsi_overbought",
      "symbol": "GOOGL",
      "timestamp": "2025-09-16T22:30:09.600527",
      "strength": -0.8,
      "confidence": 1.0,
      "description": "RSI overbought: 100.0",
      "metadata": {
        "rsi": 100.0
      }
    },
    {
      "signal_type": "rsi_overbought",
      "symbol": "MSFT",
      "timestamp": "2025-09-16T22:30:09.600711",
      "strength": -0.8,
      "confidence": 1.0,
      "description": "RSI overbought: 100.0",
      "metadata": {
        "rsi": 100.0
      }
    },
    {
      "signal_type": "rsi_overbought",
      "symbol": "AMZN",
      "timestamp": "2025-09-16T22:30:09.600968",
      "strength": -0.8,
      "confidence": 1.0,
      "description": "RSI overbought: 100.0",
      "metadata": {
        "rsi": 100.0
      }
    },
    {
      "signal_type": "rsi_overbought",
      "symbol": "TSLA",
      "timestamp": "2025-09-16T22:30:09.601146",
      "strength": -0.8,
      "confidence": 1.0,
      "description": "RSI overbought: 100.0",
      "metadata": {
        "rsi": 100.0
      }
    },
    {
      "signal_type": "rsi_overbought",
      "symbol": "NVDA",
      "timestamp": "2025-09-16T22:30:09.601300",
      "strength": -0.8,
      "confidence": 1.0,
      "description": "RSI overbought: 100.0",
      "metadata": {
        "rsi": 100.0
      }
    },
    {
      "signal_type": "rsi_overbought",
      "symbol": "META",
      "timestamp": "2025-09-16T22:30:09.601445",
      "strength": -0.8,
      "confidence": 1.0,
      "description": "RSI overbought: 100.0",
      "metadata": {
        "rsi": 100.0
      }
    },
    {
      "signal_type": "rsi_overbought",
      "symbol": "NFLX",
      "timestamp": "2025-09-16T22:30:09.601586",
      "strength": -0.8,
      "confidence": 1.0,
      "description": "RSI overbought: 100.0",
      "metadata": {
        "rsi": 100.0
      }
    },
    {
      "signal_type": "rsi_overbought",
      "symbol": "JPM",
      "timestamp": "2025-09-16T22:30:09.601724",
      "strength": -0.8,
      "confidence": 1.0,
      "description": "RSI overbought: 100.0",
      "metadata": {
        "rsi": 100.0
      }
    },
    {
      "signal_type": "rsi_overbought",
      "symbol": "BAC",
      "timestamp": "2025-09-16T22:30:09.601860",
      "strength": -0.8,
      "confidence": 1.0,
      "description": "RSI overbought: 100.0",
      "metadata": {
        "rsi": 100.0
      }
    },
    {
      "signal_type": "rsi_overbought",
      "symbol": "JNJ",
      "timestamp": "2025-09-16T22:30:09.601993",
      "strength": -0.8,
      "confidence": 1.0,
      "description": "RSI overbought: 100.0",
      "metadata": {
        "rsi": 100.0
      }
    },
    {
      "signal_type": "rsi_overbought",
      "symbol": "PFE",
      "timestamp": "2025-09-16T22:30:09.602125",
      "strength": -0.8,
      "confidence": 1.0,
      "description": "RSI overbought: 100.0",
      "metadata": {
        "rsi": 100.0
      }
    },
    {
      "signal_type": "rsi_overbought",
      "symbol": "XOM",
      "timestamp": "2025-09-16T22:30:09.602255",
      "strength": -0.8,
      "confidence": 1.0,
      "description": "RSI overbought: 100.0",
      "metadata": {
        "rsi": 100.0
      }
    },
    {
      "signal_type": "rsi_overbought",
      "symbol": "CVX",
      "timestamp": "2025-09-16T22:30:09.602385",
      "strength": -0.8,
      "confidence": 1.0,
      "description": "RSI overbought: 100.0",
      "metadata": {
        "rsi": 100.0
      }
    },
    {
      "signal_type": "rsi_overbought",
      "symbol": "WMT",
      "timestamp": "2025-09-16T22:30:09.602514",
      "strength": -0.8,
      "confidence": 1.0,
      "description": "RSI overbought: 100.0",
      "metadata": {
        "rsi": 100.0
      }
    },
    {
      "signal_type": "rsi_overbought",
      "symbol": "HD",
      "timestamp": "2025-09-16T22:30:09.602643",
      "strength": -0.8,
      "confidence": 1.0,
      "description": "RSI overbought: 100.0",
      "metadata": {
        "rsi": 100.0
      }
    },
    {
      "signal_type": "rsi_overbought",
      "symbol": "PG",
      "timestamp": "2025-09-16T22:30:09.602773",
      "strength": -0.8,
      "confidence": 1.0,
      "description": "RSI overbought: 100.0",
      "metadata": {
        "rsi": 100.0
      }
    },
    {
      "signal_type": "rsi_overbought",
      "symbol": "KO",
      "timestamp": "2025-09-16T22:30:09.602902",
      "strength": -0.8,
      "confidence": 1.0,
      "description": "RSI overbought: 100.0",
      "metadata": {
        "rsi": 100.0
      }
    },
    {
      "signal_type": "rsi_overbought",
      "symbol": "DIS",
      "timestamp": "2025-09-16T22:30:09.603031",
      "strength": -0.8,
      "confidence": 1.0,
      "description": "RSI overbought: 100.0",
      "metadata": {
        "rsi": 100.0
      }
    },
    {
      "signal_type": "rsi_overbought",
      "symbol": "V",
      "timestamp": "2025-09-16T22:30:09.603160",
      "strength": -0.8,
      "confidence": 1.0,
      "description": "RSI overbought: 100.0",
      "metadata": {
        "rsi": 100.0
      }
    }
  ],
  "heat_analysis": {
    "AAPL": {
      "symbol": "AAPL",
      "current_heat": 23.69,
      "heat_trend": "stable",
      "heat_velocity": 0.5939999999999973,
      "propagation_strength": 0.2369,
      "influenced_symbols": [],
      "analysis_timestamp": "2025-09-16T22:30:09.600507"
    },
    "GOOGL": {
      "symbol": "GOOGL",
      "current_heat": 22.68,
      "heat_trend": "stable",
      "heat_velocity": 0.4269999999999982,
      "propagation_strength": 0.2268,
      "influenced_symbols": [],
      "analysis_timestamp": "2025-09-16T22:30:09.600699"
    },
    "MSFT": {
      "symbol": "MSFT",
      "current_heat": 24.93,
      "heat_trend": "stable",
      "heat_velocity": 0.627999999999996,
      "propagation_strength": 0.2493,
      "influenced_symbols": [],
      "analysis_timestamp": "2025-09-16T22:30:09.600952"
    },
    "AMZN": {
      "symbol": "AMZN",
      "current_heat": 24.17,
      "heat_trend": "stable",
      "heat_velocity": 0.6909999999999993,
      "propagation_strength": 0.24170000000000003,
      "influenced_symbols": [],
      "analysis_timestamp": "2025-09-16T22:30:09.601134"
    },
    "TSLA": {
      "symbol": "TSLA",
      "current_heat": 15.0,
      "heat_trend": "stable",
      "heat_velocity": 0.2609999999999985,
      "propagation_strength": 0.15,
      "influenced_symbols": [],
      "analysis_timestamp": "2025-09-16T22:30:09.601290"
    },
    "NVDA": {
      "symbol": "NVDA",
      "current_heat": 22.77,
      "heat_trend": "stable",
      "heat_velocity": 0.43999999999999656,
      "propagation_strength": 0.22769999999999999,
      "influenced_symbols": [],
      "analysis_timestamp": "2025-09-16T22:30:09.601435"
    },
    "META": {
      "symbol": "META",
      "current_heat": 17.43,
      "heat_trend": "stable",
      "heat_velocity": -0.4400000000000022,
      "propagation_strength": 0.1743,
      "influenced_symbols": [],
      "analysis_timestamp": "2025-09-16T22:30:09.601576"
    },
    "NFLX": {
      "symbol": "NFLX",
      "current_heat": 17.01,
      "heat_trend": "stable",
      "heat_velocity": -0.1320000000000016,
      "propagation_strength": 0.17010000000000003,
      "influenced_symbols": [],
      "analysis_timestamp": "2025-09-16T22:30:09.601714"
    },
    "JPM": {
      "symbol": "JPM",
      "current_heat": 16.36,
      "heat_trend": "stable",
      "heat_velocity": 0.4949999999999974,
      "propagation_strength": 0.1636,
      "influenced_symbols": [],
      "analysis_timestamp": "2025-09-16T22:30:09.601851"
    },
    "BAC": {
      "symbol": "BAC",
      "current_heat": 13.86,
      "heat_trend": "stable",
      "heat_velocity": -0.1620000000000011,
      "propagation_strength": 0.1386,
      "influenced_symbols": [],
      "analysis_timestamp": "2025-09-16T22:30:09.601983"
    },
    "JNJ": {
      "symbol": "JNJ",
      "current_heat": 11.58,
      "heat_trend": "stable",
      "heat_velocity": 0.04499999999999784,
      "propagation_strength": 0.1158,
      "influenced_symbols": [],
      "analysis_timestamp": "2025-09-16T22:30:09.602115"
    },
    "PFE": {
      "symbol": "PFE",
      "current_heat": 12.85,
      "heat_trend": "stable",
      "heat_velocity": -0.14400000000000113,
      "propagation_strength": 0.1285,
      "influenced_symbols": [],
      "analysis_timestamp": "2025-09-16T22:30:09.602246"
    },
    "XOM": {
      "symbol": "XOM",
      "current_heat": 16.87,
      "heat_trend": "stable",
      "heat_velocity": -0.010000000000001083,
      "propagation_strength": 0.16870000000000002,
      "influenced_symbols": [],
      "analysis_timestamp": "2025-09-16T22:30:09.602375"
    },
    "CVX": {
      "symbol": "CVX",
      "current_heat": 13.28,
      "heat_trend": "stable",
      "heat_velocity": -0.1100000000000009,
      "propagation_strength": 0.1328,
      "influenced_symbols": [],
      "analysis_timestamp": "2025-09-16T22:30:09.602505"
    },
    "WMT": {
      "symbol": "WMT",
      "current_heat": 13.42,
      "heat_trend": "stable",
      "heat_velocity": -0.10600000000000287,
      "propagation_strength": 0.13419999999999999,
      "influenced_symbols": [],
      "analysis_timestamp": "2025-09-16T22:30:09.602634"
    },
    "HD": {
      "symbol": "HD",
      "current_heat": 13.83,
      "heat_trend": "stable",
      "heat_velocity": 0.0679999999999993,
      "propagation_strength": 0.1383,
      "influenced_symbols": [],
      "analysis_timestamp": "2025-09-16T22:30:09.602763"
    },
    "PG": {
      "symbol": "PG",
      "current_heat": 14.87,
      "heat_trend": "stable",
      "heat_velocity": 0.29899999999999877,
      "propagation_strength": 0.1487,
      "influenced_symbols": [],
      "analysis_timestamp": "2025-09-16T22:30:09.602892"
    },
    "KO": {
      "symbol": "KO",
      "current_heat": 13.78,
      "heat_trend": "stable",
      "heat_velocity": -0.16000000000000342,
      "propagation_strength": 0.1378,
      "influenced_symbols": [],
      "analysis_timestamp": "2025-09-16T22:30:09.603021"
    },
    "DIS": {
      "symbol": "DIS",
      "current_heat": 13.94,
      "heat_trend": "stable",
      "heat_velocity": -0.05800000000000175,
      "propagation_strength": 0.1394,
      "influenced_symbols": [],
      "analysis_timestamp": "2025-09-16T22:30:09.603151"
    },
    "V": {
      "symbol": "V",
      "current_heat": 13.87,
      "heat_trend": "stable",
      "heat_velocity": 0.16899999999999768,
      "propagation_strength": 0.1387,
      "influenced_symbols": [],
      "analysis_timestamp": "2025-09-16T22:30:09.603278"
    }
  },
  "analytics_status": {
    "tracked_symbols": 20,
    "data_points_per_symbol": {
      "AAPL": 100,
      "GOOGL": 100,
      "MSFT": 100,
      "AMZN": 100,
      "TSLA": 100
    },
    "active_signals": 145,
    "signal_history_size": 500,
    "heat_analysis_cache_size": 20,
    "last_analysis_time": "2025-09-16T22:30:09.603288",
    "analysis_intervals": {
      "fast": 1.0,
      "medium": 5.0,
      "slow": 30.0
    }
  }
}