{
  "timestamp": "2025-09-14T12:16:14.162514",
  "system_stats": {
    "runtime_seconds": 82212.403279,
    "data_points_generated": 65280,
    "json_files_created": 50,
    "real_data_downloads": 0,
    "analytics_signals": 47427684,
    "generation_rate": 0.7940407699609829,
    "active_symbols": 20,
    "current_regime": "bull"
  },
  "signal_summary": {
    "total_signals": 178,
    "signal_types": {
      "volume_anomaly": 81,
      "high_volume": 37,
      "rsi_overbought": 60
    },
    "average_strength": 0.755177526463963,
    "average_confidence": 0.8079310216782757,
    "timestamp": "2025-09-14T12:16:14.162618"
  },
  "active_signals": [
    {
      "signal_type": "volume_anomaly",
      "symbol": "KO",
      "timestamp": "2025-09-14T12:15:44.665264",
      "strength": 0.927778756019485,
      "confidence": 1.0,
      "description": "Volume anomaly detected: 4.93\u03c3 deviation",
      "metadata": {
        "zscore": 4.926584212361055,
        "current_volume": 60539721,
        "mean_volume": 24507961.157894738
      }
    },
    {
      "signal_type": "high_volume",
      "symbol": "KO",
      "timestamp": "2025-09-14T12:15:44.665298",
      "strength": 0.572024986196851,
      "confidence": 0.4336850174923403,
      "description": "High volume: 2.30x average",
      "metadata": {
        "volume_ratio": 2.301055052477021,
        "interpretation": "increased_interest"
      }
    },
    {
      "signal_type": "volume_anomaly",
      "symbol": "JPM",
      "timestamp": "2025-09-14T12:15:45.668861",
      "strength": 0.6968176478404113,
      "confidence": 0.6458157588978273,
      "description": "Volume anomaly detected: 2.58\u03c3 deviation",
      "metadata": {
        "zscore": 2.583263035591309,
        "current_volume": 32664846,
        "mean_volume": 20486351.315789472
      }
    },
    {
      "signal_type": "volume_anomaly",
      "symbol": "XOM",
      "timestamp": "2025-09-14T12:15:45.669458",
      "strength": 0.7114645236667408,
      "confidence": 0.6676075060987301,
      "description": "Volume anomaly detected: 2.67\u03c3 deviation",
      "metadata": {
        "zscore": 2.6704300243949204,
        "current_volume": 43250598,
        "mean_volume": 26072358.42105263
      }
    },
    {
      "signal_type": "volume_anomaly",
      "symbol": "HD",
      "timestamp": "2025-09-14T12:15:45.669891",
      "strength": 0.8731791579179959,
      "confidence": 1.0,
      "description": "Volume anomaly detected: 4.04\u03c3 deviation",
      "metadata": {
        "zscore": 4.038925428841836,
        "current_volume": 26795686,
        "mean_volume": 11092733.684210526
      }
    },
    {
      "signal_type": "high_volume",
      "symbol": "HD",
      "timestamp": "2025-09-14T12:15:45.669910",
      "strength": 0.5566498695187102,
      "confidence": 0.4186438171146453,
      "description": "High volume: 2.26x average",
      "metadata": {
        "volume_ratio": 2.255931451343936,
        "interpretation": "increased_interest"
      }
    },
    {
      "signal_type": "volume_anomaly",
      "symbol": "PFE",
      "timestamp": "2025-09-14T12:15:46.673492",
      "strength": 0.6961363633618992,
      "confidence": 0.6448234421116418,
      "description": "Volume anomaly detected: 2.58\u03c3 deviation",
      "metadata": {
        "zscore": 2.579293768446567,
        "current_volume": 78679467,
        "mean_volume": 46181135.0
      }
    },
    {
      "signal_type": "volume_anomaly",
      "symbol": "BAC",
      "timestamp": "2025-09-14T12:15:47.678004",
      "strength": 0.8253464966880788,
      "confidence": 0.880020404662189,
      "description": "Volume anomaly detected: 3.52\u03c3 deviation",
      "metadata": {
        "zscore": 3.520081618648756,
        "current_volume": 108568743,
        "mean_volume": 62979287.0
      }
    },
    {
      "signal_type": "volume_anomaly",
      "symbol": "MSFT",
      "timestamp": "2025-09-14T12:15:48.682172",
      "strength": 0.8315466554783187,
      "confidence": 0.8948464618014869,
      "description": "Volume anomaly detected: 3.58\u03c3 deviation",
      "metadata": {
        "zscore": 3.5793858472059474,
        "current_volume": 85689063,
        "mean_volume": 43499831.84210526
      }
    },
    {
      "signal_type": "volume_anomaly",
      "symbol": "NFLX",
      "timestamp": "2025-09-14T12:15:49.700738",
      "strength": 0.9814437543289355,
      "confidence": 1.0,
      "description": "Volume anomaly detected: 7.01\u03c3 deviation",
      "metadata": {
        "zscore": 7.006161900876622,
        "current_volume": 30009622,
        "mean_volume": 11422926.0
      }
    },
    {
      "signal_type": "high_volume",
      "symbol": "NFLX",
      "timestamp": "2025-09-14T12:15:49.700765",
      "strength": 0.6136418595576915,
      "confidence": 0.4764947212470341,
      "description": "High volume: 2.43x average",
      "metadata": {
        "volume_ratio": 2.4294841637411024,
        "interpretation": "increased_interest"
      }
    },
    {
      "signal_type": "volume_anomaly",
      "symbol": "NFLX",
      "timestamp": "2025-09-14T12:15:49.703593",
      "strength": 0.9814437543289355,
      "confidence": 1.0,
      "description": "Volume anomaly detected: 7.01\u03c3 deviation",
      "metadata": {
        "zscore": 7.006161900876622,
        "current_volume": 30009622,
        "mean_volume": 11422926.0
      }
    },
    {
      "signal_type": "high_volume",
      "symbol": "NFLX",
      "timestamp": "2025-09-14T12:15:49.703612",
      "strength": 0.6136418595576915,
      "confidence": 0.4764947212470341,
      "description": "High volume: 2.43x average",
      "metadata": {
        "volume_ratio": 2.4294841637411024,
        "interpretation": "increased_interest"
      }
    },
    {
      "signal_type": "volume_anomaly",
      "symbol": "NFLX",
      "timestamp": "2025-09-14T12:15:49.706349",
      "strength": 0.9814437543289355,
      "confidence": 1.0,
      "description": "Volume anomaly detected: 7.01\u03c3 deviation",
      "metadata": {
        "zscore": 7.006161900876622,
        "current_volume": 30009622,
        "mean_volume": 11422926.0
      }
    },
    {
      "signal_type": "high_volume",
      "symbol": "NFLX",
      "timestamp": "2025-09-14T12:15:49.706368",
      "strength": 0.6136418595576915,
      "confidence": 0.4764947212470341,
      "description": "High volume: 2.43x average",
      "metadata": {
        "volume_ratio": 2.4294841637411024,
        "interpretation": "increased_interest"
      }
    },
    {
      "signal_type": "volume_anomaly",
      "symbol": "NFLX",
      "timestamp": "2025-09-14T12:15:49.709094",
      "strength": 0.9814437543289355,
      "confidence": 1.0,
      "description": "Volume anomaly detected: 7.01\u03c3 deviation",
      "metadata": {
        "zscore": 7.006161900876622,
        "current_volume": 30009622,
        "mean_volume": 11422926.0
      }
    },
    {
      "signal_type": "high_volume",
      "symbol": "NFLX",
      "timestamp": "2025-09-14T12:15:49.709112",
      "strength": 0.6136418595576915,
      "confidence": 0.4764947212470341,
      "description": "High volume: 2.43x average",
      "metadata": {
        "volume_ratio": 2.4294841637411024,
        "interpretation": "increased_interest"
      }
    },
    {
      "signal_type": "volume_anomaly",
      "symbol": "NFLX",
      "timestamp": "2025-09-14T12:15:49.711849",
      "strength": 0.9814437543289355,
      "confidence": 1.0,
      "description": "Volume anomaly detected: 7.01\u03c3 deviation",
      "metadata": {
        "zscore": 7.006161900876622,
        "current_volume": 30009622,
        "mean_volume": 11422926.0
      }
    },
    {
      "signal_type": "high_volume",
      "symbol": "NFLX",
      "timestamp": "2025-09-14T12:15:49.711867",
      "strength": 0.6136418595576915,
      "confidence": 0.4764947212470341,
      "description": "High volume: 2.43x average",
      "metadata": {
        "volume_ratio": 2.4294841637411024,
        "interpretation": "increased_interest"
      }
    },
    {
      "signal_type": "volume_anomaly",
      "symbol": "NFLX",
      "timestamp": "2025-09-14T12:15:49.714617",
      "strength": 0.9814437543289355,
      "confidence": 1.0,
      "description": "Volume anomaly detected: 7.01\u03c3 deviation",
      "metadata": {
        "zscore": 7.006161900876622,
        "current_volume": 30009622,
        "mean_volume": 11422926.0
      }
    },
    {
      "signal_type": "high_volume",
      "symbol": "NFLX",
      "timestamp": "2025-09-14T12:15:49.714635",
      "strength": 0.6136418595576915,
      "confidence": 0.4764947212470341,
      "description": "High volume: 2.43x average",
      "metadata": {
        "volume_ratio": 2.4294841637411024,
        "interpretation": "increased_interest"
      }
    },
    {
      "signal_type": "volume_anomaly",
      "symbol": "NFLX",
      "timestamp": "2025-09-14T12:15:49.717368",
      "strength": 0.9814437543289355,
      "confidence": 1.0,
      "description": "Volume anomaly detected: 7.01\u03c3 deviation",
      "metadata": {
        "zscore": 7.006161900876622,
        "current_volume": 30009622,
        "mean_volume": 11422926.0
      }
    },
    {
      "signal_type": "high_volume",
      "symbol": "NFLX",
      "timestamp": "2025-09-14T12:15:49.717385",
      "strength": 0.6136418595576915,
      "confidence": 0.4764947212470341,
      "description": "High volume: 2.43x average",
      "metadata": {
        "volume_ratio": 2.4294841637411024,
        "interpretation": "increased_interest"
      }
    },
    {
      "signal_type": "volume_anomaly",
      "symbol": "NFLX",
      "timestamp": "2025-09-14T12:15:49.720118",
      "strength": 0.9814437543289355,
      "confidence": 1.0,
      "description": "Volume anomaly detected: 7.01\u03c3 deviation",
      "metadata": {
        "zscore": 7.006161900876622,
        "current_volume": 30009622,
        "mean_volume": 11422926.0
      }
    },
    {
      "signal_type": "high_volume",
      "symbol": "NFLX",
      "timestamp": "2025-09-14T12:15:49.720136",
      "strength": 0.6136418595576915,
      "confidence": 0.4764947212470341,
      "description": "High volume: 2.43x average",
      "metadata": {
        "volume_ratio": 2.4294841637411024,
        "interpretation": "increased_interest"
      }
    },
    {
      "signal_type": "volume_anomaly",
      "symbol": "NFLX",
      "timestamp": "2025-09-14T12:15:49.722863",
      "strength": 0.9814437543289355,
      "confidence": 1.0,
      "description": "Volume anomaly detected: 7.01\u03c3 deviation",
      "metadata": {
        "zscore": 7.006161900876622,
        "current_volume": 30009622,
        "mean_volume": 11422926.0
      }
    },
    {
      "signal_type": "high_volume",
      "symbol": "NFLX",
      "timestamp": "2025-09-14T12:15:49.722881",
      "strength": 0.6136418595576915,
      "confidence": 0.4764947212470341,
      "description": "High volume: 2.43x average",
      "metadata": {
        "volume_ratio": 2.4294841637411024,
        "interpretation": "increased_interest"
      }
    },
    {
      "signal_type": "volume_anomaly",
      "symbol": "NFLX",
      "timestamp": "2025-09-14T12:15:49.725603",
      "strength": 0.9814437543289355,
      "confidence": 1.0,
      "description": "Volume anomaly detected: 7.01\u03c3 deviation",
      "metadata": {
        "zscore": 7.006161900876622,
        "current_volume": 30009622,
        "mean_volume": 11422926.0
      }
    },
    {
      "signal_type": "high_volume",
      "symbol": "NFLX",
      "timestamp": "2025-09-14T12:15:49.725621",
      "strength": 0.6136418595576915,
      "confidence": 0.4764947212470341,
      "description": "High volume: 2.43x average",
      "metadata": {
        "volume_ratio": 2.4294841637411024,
        "interpretation": "increased_interest"
      }
    },
    {
      "signal_type": "volume_anomaly",
      "symbol": "NFLX",
      "timestamp": "2025-09-14T12:15:49.728353",
      "strength": 0.9814437543289355,
      "confidence": 1.0,
      "description": "Volume anomaly detected: 7.01\u03c3 deviation",
      "metadata": {
        "zscore": 7.006161900876622,
        "current_volume": 30009622,
        "mean_volume": 11422926.0
      }
    },
    {
      "signal_type": "high_volume",
      "symbol": "NFLX",
      "timestamp": "2025-09-14T12:15:49.728371",
      "strength": 0.6136418595576915,
      "confidence": 0.4764947212470341,
      "description": "High volume: 2.43x average",
      "metadata": {
        "volume_ratio": 2.4294841637411024,
        "interpretation": "increased_interest"
      }
    },
    {
      "signal_type": "volume_anomaly",
      "symbol": "NFLX",
      "timestamp": "2025-09-14T12:15:49.731208",
      "strength": 0.9814437543289355,
      "confidence": 1.0,
      "description": "Volume anomaly detected: 7.01\u03c3 deviation",
      "metadata": {
        "zscore": 7.006161900876622,
        "current_volume": 30009622,
        "mean_volume": 11422926.0
      }
    },
    {
      "signal_type": "high_volume",
      "symbol": "NFLX",
      "timestamp": "2025-09-14T12:15:49.731228",
      "strength": 0.6136418595576915,
      "confidence": 0.4764947212470341,
      "description": "High volume: 2.43x average",
      "metadata": {
        "volume_ratio": 2.4294841637411024,
        "interpretation": "increased_interest"
      }
    },
    {
      "signal_type": "rsi_overbought",
      "symbol": "AAPL",
      "timestamp": "2025-09-14T12:15:51.740960",
      "strength": -0.8,
      "confidence": 1.0,
      "description": "RSI overbought: 100.0",
      "metadata": {
        "rsi": 100.0
      }
    },
    {
      "signal_type": "rsi_overbought",
      "symbol": "GOOGL",
      "timestamp": "2025-09-14T12:15:51.741385",
      "strength": -0.8,
      "confidence": 1.0,
      "description": "RSI overbought: 100.0",
      "metadata": {
        "rsi": 100.0
      }
    },
    {
      "signal_type": "rsi_overbought",
      "symbol": "MSFT",
      "timestamp": "2025-09-14T12:15:51.741687",
      "strength": -0.8,
      "confidence": 1.0,
      "description": "RSI overbought: 100.0",
      "metadata": {
        "rsi": 100.0
      }
    },
    {
      "signal_type": "rsi_overbought",
      "symbol": "AMZN",
      "timestamp": "2025-09-14T12:15:51.741901",
      "strength": -0.8,
      "confidence": 1.0,
      "description": "RSI overbought: 100.0",
      "metadata": {
        "rsi": 100.0
      }
    },
    {
      "signal_type": "rsi_overbought",
      "symbol": "TSLA",
      "timestamp": "2025-09-14T12:15:51.742098",
      "strength": -0.8,
      "confidence": 1.0,
      "description": "RSI overbought: 100.0",
      "metadata": {
        "rsi": 100.0
      }
    },
    {
      "signal_type": "rsi_overbought",
      "symbol": "NVDA",
      "timestamp": "2025-09-14T12:15:51.742284",
      "strength": -0.8,
      "confidence": 1.0,
      "description": "RSI overbought: 100.0",
      "metadata": {
        "rsi": 100.0
      }
    },
    {
      "signal_type": "rsi_overbought",
      "symbol": "META",
      "timestamp": "2025-09-14T12:15:51.742520",
      "strength": -0.8,
      "confidence": 1.0,
      "description": "RSI overbought: 100.0",
      "metadata": {
        "rsi": 100.0
      }
    },
    {
      "signal_type": "rsi_overbought",
      "symbol": "NFLX",
      "timestamp": "2025-09-14T12:15:51.742791",
      "strength": -0.8,
      "confidence": 1.0,
      "description": "RSI overbought: 100.0",
      "metadata": {
        "rsi": 100.0
      }
    },
    {
      "signal_type": "rsi_overbought",
      "symbol": "JPM",
      "timestamp": "2025-09-14T12:15:51.742990",
      "strength": -0.8,
      "confidence": 1.0,
      "description": "RSI overbought: 100.0",
      "metadata": {
        "rsi": 100.0
      }
    },
    {
      "signal_type": "rsi_overbought",
      "symbol": "BAC",
      "timestamp": "2025-09-14T12:15:51.743144",
      "strength": -0.8,
      "confidence": 1.0,
      "description": "RSI overbought: 100.0",
      "metadata": {
        "rsi": 100.0
      }
    },
    {
      "signal_type": "rsi_overbought",
      "symbol": "JNJ",
      "timestamp": "2025-09-14T12:15:51.743292",
      "strength": -0.8,
      "confidence": 1.0,
      "description": "RSI overbought: 100.0",
      "metadata": {
        "rsi": 100.0
      }
    },
    {
      "signal_type": "rsi_overbought",
      "symbol": "PFE",
      "timestamp": "2025-09-14T12:15:51.743438",
      "strength": -0.8,
      "confidence": 1.0,
      "description": "RSI overbought: 100.0",
      "metadata": {
        "rsi": 100.0
      }
    },
    {
      "signal_type": "rsi_overbought",
      "symbol": "XOM",
      "timestamp": "2025-09-14T12:15:51.743582",
      "strength": -0.8,
      "confidence": 1.0,
      "description": "RSI overbought: 100.0",
      "metadata": {
        "rsi": 100.0
      }
    },
    {
      "signal_type": "rsi_overbought",
      "symbol": "CVX",
      "timestamp": "2025-09-14T12:15:51.743721",
      "strength": -0.8,
      "confidence": 1.0,
      "description": "RSI overbought: 100.0",
      "metadata": {
        "rsi": 100.0
      }
    },
    {
      "signal_type": "rsi_overbought",
      "symbol": "WMT",
      "timestamp": "2025-09-14T12:15:51.743860",
      "strength": -0.8,
      "confidence": 1.0,
      "description": "RSI overbought: 100.0",
      "metadata": {
        "rsi": 100.0
      }
    },
    {
      "signal_type": "rsi_overbought",
      "symbol": "HD",
      "timestamp": "2025-09-14T12:15:51.743996",
      "strength": -0.8,
      "confidence": 1.0,
      "description": "RSI overbought: 100.0",
      "metadata": {
        "rsi": 100.0
      }
    },
    {
      "signal_type": "rsi_overbought",
      "symbol": "PG",
      "timestamp": "2025-09-14T12:15:51.744134",
      "strength": -0.8,
      "confidence": 1.0,
      "description": "RSI overbought: 100.0",
      "metadata": {
        "rsi": 100.0
      }
    },
    {
      "signal_type": "rsi_overbought",
      "symbol": "KO",
      "timestamp": "2025-09-14T12:15:51.744270",
      "strength": -0.8,
      "confidence": 1.0,
      "description": "RSI overbought: 100.0",
      "metadata": {
        "rsi": 100.0
      }
    },
    {
      "signal_type": "rsi_overbought",
      "symbol": "DIS",
      "timestamp": "2025-09-14T12:15:51.744406",
      "strength": -0.8,
      "confidence": 1.0,
      "description": "RSI overbought: 100.0",
      "metadata": {
        "rsi": 100.0
      }
    },
    {
      "signal_type": "rsi_overbought",
      "symbol": "V",
      "timestamp": "2025-09-14T12:15:51.744540",
      "strength": -0.8,
      "confidence": 1.0,
      "description": "RSI overbought: 100.0",
      "metadata": {
        "rsi": 100.0
      }
    },
    {
      "signal_type": "volume_anomaly",
      "symbol": "CVX",
      "timestamp": "2025-09-14T12:15:52.751050",
      "strength": 0.787368664521262,
      "confidence": 0.7983524815172719,
      "description": "Volume anomaly detected: 3.19\u03c3 deviation",
      "metadata": {
        "zscore": 3.1934099260690876,
        "current_volume": 32800423,
        "mean_volume": 15983434.789473685
      }
    },
    {
      "signal_type": "volume_anomaly",
      "symbol": "NVDA",
      "timestamp": "2025-09-14T12:15:54.759338",
      "strength": 0.7809115172614379,
      "confidence": 0.7857768455906334,
      "description": "Volume anomaly detected: 3.14\u03c3 deviation",
      "metadata": {
        "zscore": 3.1431073823625337,
        "current_volume": 94596326,
        "mean_volume": 55111897.89473684
      }
    },
    {
      "signal_type": "volume_anomaly",
      "symbol": "JNJ",
      "timestamp": "2025-09-14T12:15:55.766917",
      "strength": 0.7985794022116779,
      "confidence": 0.821008936202463,
      "description": "Volume anomaly detected: 3.28\u03c3 deviation",
      "metadata": {
        "zscore": 3.284035744809852,
        "current_volume": 26621937,
        "mean_volume": 15603794.94736842
      }
    },
    {
      "signal_type": "volume_anomaly",
      "symbol": "GOOGL",
      "timestamp": "2025-09-14T12:15:56.773561",
      "strength": 0.7243271528457818,
      "confidence": 0.687516514049945,
      "description": "Volume anomaly detected: 2.75\u03c3 deviation",
      "metadata": {
        "zscore": 2.75006605619978,
        "current_volume": 62011874,
        "mean_volume": 34168536.2631579
      }
    },
    {
      "signal_type": "volume_anomaly",
      "symbol": "PFE",
      "timestamp": "2025-09-14T12:15:56.776865",
      "strength": 0.7781539560224517,
      "confidence": 0.780505258525427,
      "description": "Volume anomaly detected: 3.12\u03c3 deviation",
      "metadata": {
        "zscore": 3.122021034101708,
        "current_volume": 104422889,
        "mean_volume": 51825865.368421055
      }
    },
    {
      "signal_type": "volume_anomaly",
      "symbol": "XOM",
      "timestamp": "2025-09-14T12:15:57.783325",
      "strength": 0.7028889261459792,
      "confidence": 0.6547407754293977,
      "description": "Volume anomaly detected: 2.62\u03c3 deviation",
      "metadata": {
        "zscore": 2.6189631017175907,
        "current_volume": 42670609,
        "mean_volume": 26399665.157894738
      }
    },
    {
      "signal_type": "volume_anomaly",
      "symbol": "DIS",
      "timestamp": "2025-09-14T12:15:57.784169",
      "strength": 0.8227834932651518,
      "confidence": 0.8740304312558805,
      "description": "Volume anomaly detected: 3.50\u03c3 deviation",
      "metadata": {
        "zscore": 3.496121725023522,
        "current_volume": 26660542,
        "mean_volume": 16114636.894736841
      }
    },
    {
      "signal_type": "volume_anomaly",
      "symbol": "PG",
      "timestamp": "2025-09-14T12:15:59.795189",
      "strength": 0.7504222173453088,
      "confidence": 0.7304406315519131,
      "description": "Volume anomaly detected: 2.92\u03c3 deviation",
      "metadata": {
        "zscore": 2.9217625262076523,
        "current_volume": 20429448,
        "mean_volume": 11744594.578947369
      }
    },
    {
      "signal_type": "volume_anomaly",
      "symbol": "XOM",
      "timestamp": "2025-09-14T12:16:00.798162",
      "strength": 0.7894411940045526,
      "confidence": 0.8024601339258409,
      "description": "Volume anomaly detected: 3.21\u03c3 deviation",
      "metadata": {
        "zscore": 3.2098405357033637,
        "current_volume": 50668006,
        "mean_volume": 27350422.47368421
      }
    },
    {
      "signal_type": "volume_anomaly",
      "symbol": "MSFT",
      "timestamp": "2025-09-14T12:16:01.801075",
      "strength": 0.7995583532024966,
      "confidence": 0.823040020678688,
      "description": "Volume anomaly detected: 3.29\u03c3 deviation",
      "metadata": {
        "zscore": 3.292160082714752,
        "current_volume": 92080754,
        "mean_volume": 49587693.15789474
      }
    },
    {
      "signal_type": "rsi_overbought",
      "symbol": "AAPL",
      "timestamp": "2025-09-14T12:16:02.805359",
      "strength": -0.8,
      "confidence": 1.0,
      "description": "RSI overbought: 100.0",
      "metadata": {
        "rsi": 100.0
      }
    },
    {
      "signal_type": "rsi_overbought",
      "symbol": "GOOGL",
      "timestamp": "2025-09-14T12:16:02.805718",
      "strength": -0.8,
      "confidence": 1.0,
      "description": "RSI overbought: 100.0",
      "metadata": {
        "rsi": 100.0
      }
    },
    {
      "signal_type": "rsi_overbought",
      "symbol": "MSFT",
      "timestamp": "2025-09-14T12:16:02.805939",
      "strength": -0.8,
      "confidence": 1.0,
      "description": "RSI overbought: 100.0",
      "metadata": {
        "rsi": 100.0
      }
    },
    {
      "signal_type": "rsi_overbought",
      "symbol": "AMZN",
      "timestamp": "2025-09-14T12:16:02.806140",
      "strength": -0.8,
      "confidence": 1.0,
      "description": "RSI overbought: 100.0",
      "metadata": {
        "rsi": 100.0
      }
    },
    {
      "signal_type": "rsi_overbought",
      "symbol": "TSLA",
      "timestamp": "2025-09-14T12:16:02.806348",
      "strength": -0.8,
      "confidence": 1.0,
      "description": "RSI overbought: 100.0",
      "metadata": {
        "rsi": 100.0
      }
    },
    {
      "signal_type": "rsi_overbought",
      "symbol": "NVDA",
      "timestamp": "2025-09-14T12:16:02.806534",
      "strength": -0.8,
      "confidence": 1.0,
      "description": "RSI overbought: 100.0",
      "metadata": {
        "rsi": 100.0
      }
    },
    {
      "signal_type": "rsi_overbought",
      "symbol": "META",
      "timestamp": "2025-09-14T12:16:02.806713",
      "strength": -0.8,
      "confidence": 1.0,
      "description": "RSI overbought: 100.0",
      "metadata": {
        "rsi": 100.0
      }
    },
    {
      "signal_type": "rsi_overbought",
      "symbol": "NFLX",
      "timestamp": "2025-09-14T12:16:02.806887",
      "strength": -0.8,
      "confidence": 1.0,
      "description": "RSI overbought: 100.0",
      "metadata": {
        "rsi": 100.0
      }
    },
    {
      "signal_type": "rsi_overbought",
      "symbol": "JPM",
      "timestamp": "2025-09-14T12:16:02.807061",
      "strength": -0.8,
      "confidence": 1.0,
      "description": "RSI overbought: 100.0",
      "metadata": {
        "rsi": 100.0
      }
    },
    {
      "signal_type": "rsi_overbought",
      "symbol": "BAC",
      "timestamp": "2025-09-14T12:16:02.807234",
      "strength": -0.8,
      "confidence": 1.0,
      "description": "RSI overbought: 100.0",
      "metadata": {
        "rsi": 100.0
      }
    },
    {
      "signal_type": "rsi_overbought",
      "symbol": "JNJ",
      "timestamp": "2025-09-14T12:16:02.807409",
      "strength": -0.8,
      "confidence": 1.0,
      "description": "RSI overbought: 100.0",
      "metadata": {
        "rsi": 100.0
      }
    },
    {
      "signal_type": "rsi_overbought",
      "symbol": "PFE",
      "timestamp": "2025-09-14T12:16:02.807554",
      "strength": -0.8,
      "confidence": 1.0,
      "description": "RSI overbought: 100.0",
      "metadata": {
        "rsi": 100.0
      }
    },
    {
      "signal_type": "rsi_overbought",
      "symbol": "XOM",
      "timestamp": "2025-09-14T12:16:02.807696",
      "strength": -0.8,
      "confidence": 1.0,
      "description": "RSI overbought: 100.0",
      "metadata": {
        "rsi": 100.0
      }
    },
    {
      "signal_type": "rsi_overbought",
      "symbol": "CVX",
      "timestamp": "2025-09-14T12:16:02.807838",
      "strength": -0.8,
      "confidence": 1.0,
      "description": "RSI overbought: 100.0",
      "metadata": {
        "rsi": 100.0
      }
    },
    {
      "signal_type": "rsi_overbought",
      "symbol": "WMT",
      "timestamp": "2025-09-14T12:16:02.807978",
      "strength": -0.8,
      "confidence": 1.0,
      "description": "RSI overbought: 100.0",
      "metadata": {
        "rsi": 100.0
      }
    },
    {
      "signal_type": "rsi_overbought",
      "symbol": "HD",
      "timestamp": "2025-09-14T12:16:02.808131",
      "strength": -0.8,
      "confidence": 1.0,
      "description": "RSI overbought: 100.0",
      "metadata": {
        "rsi": 100.0
      }
    },
    {
      "signal_type": "rsi_overbought",
      "symbol": "PG",
      "timestamp": "2025-09-14T12:16:02.808266",
      "strength": -0.8,
      "confidence": 1.0,
      "description": "RSI overbought: 100.0",
      "metadata": {
        "rsi": 100.0
      }
    },
    {
      "signal_type": "rsi_overbought",
      "symbol": "KO",
      "timestamp": "2025-09-14T12:16:02.808401",
      "strength": -0.8,
      "confidence": 1.0,
      "description": "RSI overbought: 100.0",
      "metadata": {
        "rsi": 100.0
      }
    },
    {
      "signal_type": "rsi_overbought",
      "symbol": "DIS",
      "timestamp": "2025-09-14T12:16:02.808536",
      "strength": -0.8,
      "confidence": 1.0,
      "description": "RSI overbought: 100.0",
      "metadata": {
        "rsi": 100.0
      }
    },
    {
      "signal_type": "rsi_overbought",
      "symbol": "V",
      "timestamp": "2025-09-14T12:16:02.808672",
      "strength": -0.8,
      "confidence": 1.0,
      "description": "RSI overbought: 100.0",
      "metadata": {
        "rsi": 100.0
      }
    },
    {
      "signal_type": "volume_anomaly",
      "symbol": "TSLA",
      "timestamp": "2025-09-14T12:16:03.814650",
      "strength": 0.8124394220069086,
      "confidence": 0.8506226579883537,
      "description": "Volume anomaly detected: 3.40\u03c3 deviation",
      "metadata": {
        "zscore": 3.4024906319534147,
        "current_volume": 114025952,
        "mean_volume": 62131863.315789476
      }
    },
    {
      "signal_type": "volume_anomaly",
      "symbol": "HD",
      "timestamp": "2025-09-14T12:16:03.816913",
      "strength": 0.7219658313394953,
      "confidence": 0.6838041852654039,
      "description": "Volume anomaly detected: 2.74\u03c3 deviation",
      "metadata": {
        "zscore": 2.7352167410616155,
        "current_volume": 20124230,
        "mean_volume": 12576154.842105264
      }
    },
    {
      "signal_type": "volume_anomaly",
      "symbol": "DIS",
      "timestamp": "2025-09-14T12:16:05.825895",
      "strength": 0.7078113247338563,
      "confidence": 0.6620880603217826,
      "description": "Volume anomaly detected: 2.65\u03c3 deviation",
      "metadata": {
        "zscore": 2.6483522412871303,
        "current_volume": 32484029,
        "mean_volume": 18214875.47368421
      }
    },
    {
      "signal_type": "volume_anomaly",
      "symbol": "CVX",
      "timestamp": "2025-09-14T12:16:06.829344",
      "strength": 0.8639087358351024,
      "confidence": 0.9814144919524019,
      "description": "Volume anomaly detected: 3.93\u03c3 deviation",
      "metadata": {
        "zscore": 3.9256579678096077,
        "current_volume": 39162739,
        "mean_volume": 17265770.684210528
      }
    },
    {
      "signal_type": "high_volume",
      "symbol": "CVX",
      "timestamp": "2025-09-14T12:16:06.829376",
      "strength": 0.5127749630124937,
      "confidence": 0.37765828749569047,
      "description": "High volume: 2.13x average",
      "metadata": {
        "volume_ratio": 2.1329748624870715,
        "interpretation": "increased_interest"
      }
    },
    {
      "signal_type": "volume_anomaly",
      "symbol": "GOOGL",
      "timestamp": "2025-09-14T12:16:07.831613",
      "strength": 0.7021010783353825,
      "confidence": 0.6535741707836915,
      "description": "Volume anomaly detected: 2.61\u03c3 deviation",
      "metadata": {
        "zscore": 2.614296683134766,
        "current_volume": 56215353,
        "mean_volume": 33006923.94736842
      }
    },
    {
      "signal_type": "volume_anomaly",
      "symbol": "META",
      "timestamp": "2025-09-14T12:16:09.841818",
      "strength": 0.7717198347347096,
      "confidence": 0.768424628335888,
      "description": "Volume anomaly detected: 3.07\u03c3 deviation",
      "metadata": {
        "zscore": 3.073698513343552,
        "current_volume": 63102076,
        "mean_volume": 36439156.684210524
      }
    },
    {
      "signal_type": "volume_anomaly",
      "symbol": "GOOGL",
      "timestamp": "2025-09-14T12:16:10.844971",
      "strength": 0.7681018212936561,
      "confidence": 0.7617612908726327,
      "description": "Volume anomaly detected: 3.05\u03c3 deviation",
      "metadata": {
        "zscore": 3.0470451634905307,
        "current_volume": 69252612,
        "mean_volume": 34399847.0
      }
    },
    {
      "signal_type": "volume_anomaly",
      "symbol": "AMZN",
      "timestamp": "2025-09-14T12:16:10.845302",
      "strength": 0.7128736195738345,
      "confidence": 0.6697519686012163,
      "description": "Volume anomaly detected: 2.68\u03c3 deviation",
      "metadata": {
        "zscore": 2.6790078744048653,
        "current_volume": 73759185,
        "mean_volume": 41828063.2631579
      }
    },
    {
      "signal_type": "volume_anomaly",
      "symbol": "AAPL",
      "timestamp": "2025-09-14T12:16:11.988565",
      "strength": 0.8754589042353225,
      "confidence": 1.0,
      "description": "Volume anomaly detected: 4.07\u03c3 deviation",
      "metadata": {
        "zscore": 4.0679593642236,
        "current_volume": 229989890,
        "mean_volume": 104896643.42105263
      }
    },
    {
      "signal_type": "high_volume",
      "symbol": "AAPL",
      "timestamp": "2025-09-14T12:16:11.988615",
      "strength": 0.4888744619933754,
      "confidence": 0.35638682919086334,
      "description": "High volume: 2.07x average",
      "metadata": {
        "volume_ratio": 2.06916048757259,
        "interpretation": "increased_interest"
      }
    },
    {
      "signal_type": "volume_anomaly",
      "symbol": "NFLX",
      "timestamp": "2025-09-14T12:16:11.991381",
      "strength": 0.7327756947032078,
      "confidence": 0.7010217934061826,
      "description": "Volume anomaly detected: 2.80\u03c3 deviation",
      "metadata": {
        "zscore": 2.8040871736247306,
        "current_volume": 21626291,
        "mean_volume": 11564568.05263158
      }
    },
    {
      "signal_type": "volume_anomaly",
      "symbol": "AAPL",
      "timestamp": "2025-09-14T12:16:11.994945",
      "strength": 0.8754589042353225,
      "confidence": 1.0,
      "description": "Volume anomaly detected: 4.07\u03c3 deviation",
      "metadata": {
        "zscore": 4.0679593642236,
        "current_volume": 229989890,
        "mean_volume": 104896643.42105263
      }
    },
    {
      "signal_type": "high_volume",
      "symbol": "AAPL",
      "timestamp": "2025-09-14T12:16:11.994992",
      "strength": 0.4888744619933754,
      "confidence": 0.35638682919086334,
      "description": "High volume: 2.07x average",
      "metadata": {
        "volume_ratio": 2.06916048757259,
        "interpretation": "increased_interest"
      }
    },
    {
      "signal_type": "volume_anomaly",
      "symbol": "NFLX",
      "timestamp": "2025-09-14T12:16:11.996823",
      "strength": 0.7327756947032078,
      "confidence": 0.7010217934061826,
      "description": "Volume anomaly detected: 2.80\u03c3 deviation",
      "metadata": {
        "zscore": 2.8040871736247306,
        "current_volume": 21626291,
        "mean_volume": 11564568.05263158
      }
    },
    {
      "signal_type": "volume_anomaly",
      "symbol": "AAPL",
      "timestamp": "2025-09-14T12:16:12.001797",
      "strength": 0.8754589042353225,
      "confidence": 1.0,
      "description": "Volume anomaly detected: 4.07\u03c3 deviation",
      "metadata": {
        "zscore": 4.0679593642236,
        "current_volume": 229989890,
        "mean_volume": 104896643.42105263
      }
    },
    {
      "signal_type": "high_volume",
      "symbol": "AAPL",
      "timestamp": "2025-09-14T12:16:12.001843",
      "strength": 0.4888744619933754,
      "confidence": 0.35638682919086334,
      "description": "High volume: 2.07x average",
      "metadata": {
        "volume_ratio": 2.06916048757259,
        "interpretation": "increased_interest"
      }
    },
    {
      "signal_type": "volume_anomaly",
      "symbol": "NFLX",
      "timestamp": "2025-09-14T12:16:12.003937",
      "strength": 0.7327756947032078,
      "confidence": 0.7010217934061826,
      "description": "Volume anomaly detected: 2.80\u03c3 deviation",
      "metadata": {
        "zscore": 2.8040871736247306,
        "current_volume": 21626291,
        "mean_volume": 11564568.05263158
      }
    },
    {
      "signal_type": "volume_anomaly",
      "symbol": "AAPL",
      "timestamp": "2025-09-14T12:16:12.007871",
      "strength": 0.8754589042353225,
      "confidence": 1.0,
      "description": "Volume anomaly detected: 4.07\u03c3 deviation",
      "metadata": {
        "zscore": 4.0679593642236,
        "current_volume": 229989890,
        "mean_volume": 104896643.42105263
      }
    },
    {
      "signal_type": "high_volume",
      "symbol": "AAPL",
      "timestamp": "2025-09-14T12:16:12.007914",
      "strength": 0.4888744619933754,
      "confidence": 0.35638682919086334,
      "description": "High volume: 2.07x average",
      "metadata": {
        "volume_ratio": 2.06916048757259,
        "interpretation": "increased_interest"
      }
    },
    {
      "signal_type": "volume_anomaly",
      "symbol": "NFLX",
      "timestamp": "2025-09-14T12:16:12.010245",
      "strength": 0.7327756947032078,
      "confidence": 0.7010217934061826,
      "description": "Volume anomaly detected: 2.80\u03c3 deviation",
      "metadata": {
        "zscore": 2.8040871736247306,
        "current_volume": 21626291,
        "mean_volume": 11564568.05263158
      }
    },
    {
      "signal_type": "volume_anomaly",
      "symbol": "AAPL",
      "timestamp": "2025-09-14T12:16:12.014659",
      "strength": 0.8754589042353225,
      "confidence": 1.0,
      "description": "Volume anomaly detected: 4.07\u03c3 deviation",
      "metadata": {
        "zscore": 4.0679593642236,
        "current_volume": 229989890,
        "mean_volume": 104896643.42105263
      }
    },
    {
      "signal_type": "high_volume",
      "symbol": "AAPL",
      "timestamp": "2025-09-14T12:16:12.014702",
      "strength": 0.4888744619933754,
      "confidence": 0.35638682919086334,
      "description": "High volume: 2.07x average",
      "metadata": {
        "volume_ratio": 2.06916048757259,
        "interpretation": "increased_interest"
      }
    },
    {
      "signal_type": "volume_anomaly",
      "symbol": "NFLX",
      "timestamp": "2025-09-14T12:16:12.017061",
      "strength": 0.7327756947032078,
      "confidence": 0.7010217934061826,
      "description": "Volume anomaly detected: 2.80\u03c3 deviation",
      "metadata": {
        "zscore": 2.8040871736247306,
        "current_volume": 21626291,
        "mean_volume": 11564568.05263158
      }
    },
    {
      "signal_type": "volume_anomaly",
      "symbol": "AAPL",
      "timestamp": "2025-09-14T12:16:12.021943",
      "strength": 0.8754589042353225,
      "confidence": 1.0,
      "description": "Volume anomaly detected: 4.07\u03c3 deviation",
      "metadata": {
        "zscore": 4.0679593642236,
        "current_volume": 229989890,
        "mean_volume": 104896643.42105263
      }
    },
    {
      "signal_type": "high_volume",
      "symbol": "AAPL",
      "timestamp": "2025-09-14T12:16:12.022010",
      "strength": 0.4888744619933754,
      "confidence": 0.35638682919086334,
      "description": "High volume: 2.07x average",
      "metadata": {
        "volume_ratio": 2.06916048757259,
        "interpretation": "increased_interest"
      }
    },
    {
      "signal_type": "volume_anomaly",
      "symbol": "NFLX",
      "timestamp": "2025-09-14T12:16:12.024034",
      "strength": 0.7327756947032078,
      "confidence": 0.7010217934061826,
      "description": "Volume anomaly detected: 2.80\u03c3 deviation",
      "metadata": {
        "zscore": 2.8040871736247306,
        "current_volume": 21626291,
        "mean_volume": 11564568.05263158
      }
    },
    {
      "signal_type": "volume_anomaly",
      "symbol": "AAPL",
      "timestamp": "2025-09-14T12:16:12.028551",
      "strength": 0.8754589042353225,
      "confidence": 1.0,
      "description": "Volume anomaly detected: 4.07\u03c3 deviation",
      "metadata": {
        "zscore": 4.0679593642236,
        "current_volume": 229989890,
        "mean_volume": 104896643.42105263
      }
    },
    {
      "signal_type": "high_volume",
      "symbol": "AAPL",
      "timestamp": "2025-09-14T12:16:12.028596",
      "strength": 0.4888744619933754,
      "confidence": 0.35638682919086334,
      "description": "High volume: 2.07x average",
      "metadata": {
        "volume_ratio": 2.06916048757259,
        "interpretation": "increased_interest"
      }
    },
    {
      "signal_type": "volume_anomaly",
      "symbol": "NFLX",
      "timestamp": "2025-09-14T12:16:12.030865",
      "strength": 0.7327756947032078,
      "confidence": 0.7010217934061826,
      "description": "Volume anomaly detected: 2.80\u03c3 deviation",
      "metadata": {
        "zscore": 2.8040871736247306,
        "current_volume": 21626291,
        "mean_volume": 11564568.05263158
      }
    },
    {
      "signal_type": "volume_anomaly",
      "symbol": "AAPL",
      "timestamp": "2025-09-14T12:16:12.036762",
      "strength": 0.8754589042353225,
      "confidence": 1.0,
      "description": "Volume anomaly detected: 4.07\u03c3 deviation",
      "metadata": {
        "zscore": 4.0679593642236,
        "current_volume": 229989890,
        "mean_volume": 104896643.42105263
      }
    },
    {
      "signal_type": "high_volume",
      "symbol": "AAPL",
      "timestamp": "2025-09-14T12:16:12.036807",
      "strength": 0.4888744619933754,
      "confidence": 0.35638682919086334,
      "description": "High volume: 2.07x average",
      "metadata": {
        "volume_ratio": 2.06916048757259,
        "interpretation": "increased_interest"
      }
    },
    {
      "signal_type": "volume_anomaly",
      "symbol": "NFLX",
      "timestamp": "2025-09-14T12:16:12.039046",
      "strength": 0.7327756947032078,
      "confidence": 0.7010217934061826,
      "description": "Volume anomaly detected: 2.80\u03c3 deviation",
      "metadata": {
        "zscore": 2.8040871736247306,
        "current_volume": 21626291,
        "mean_volume": 11564568.05263158
      }
    },
    {
      "signal_type": "volume_anomaly",
      "symbol": "AAPL",
      "timestamp": "2025-09-14T12:16:12.042866",
      "strength": 0.8754589042353225,
      "confidence": 1.0,
      "description": "Volume anomaly detected: 4.07\u03c3 deviation",
      "metadata": {
        "zscore": 4.0679593642236,
        "current_volume": 229989890,
        "mean_volume": 104896643.42105263
      }
    },
    {
      "signal_type": "high_volume",
      "symbol": "AAPL",
      "timestamp": "2025-09-14T12:16:12.042913",
      "strength": 0.4888744619933754,
      "confidence": 0.35638682919086334,
      "description": "High volume: 2.07x average",
      "metadata": {
        "volume_ratio": 2.06916048757259,
        "interpretation": "increased_interest"
      }
    },
    {
      "signal_type": "volume_anomaly",
      "symbol": "NFLX",
      "timestamp": "2025-09-14T12:16:12.045719",
      "strength": 0.7327756947032078,
      "confidence": 0.7010217934061826,
      "description": "Volume anomaly detected: 2.80\u03c3 deviation",
      "metadata": {
        "zscore": 2.8040871736247306,
        "current_volume": 21626291,
        "mean_volume": 11564568.05263158
      }
    },
    {
      "signal_type": "volume_anomaly",
      "symbol": "AAPL",
      "timestamp": "2025-09-14T12:16:12.051224",
      "strength": 0.8754589042353225,
      "confidence": 1.0,
      "description": "Volume anomaly detected: 4.07\u03c3 deviation",
      "metadata": {
        "zscore": 4.0679593642236,
        "current_volume": 229989890,
        "mean_volume": 104896643.42105263
      }
    },
    {
      "signal_type": "high_volume",
      "symbol": "AAPL",
      "timestamp": "2025-09-14T12:16:12.051271",
      "strength": 0.4888744619933754,
      "confidence": 0.35638682919086334,
      "description": "High volume: 2.07x average",
      "metadata": {
        "volume_ratio": 2.06916048757259,
        "interpretation": "increased_interest"
      }
    },
    {
      "signal_type": "volume_anomaly",
      "symbol": "NFLX",
      "timestamp": "2025-09-14T12:16:12.052682",
      "strength": 0.7327756947032078,
      "confidence": 0.7010217934061826,
      "description": "Volume anomaly detected: 2.80\u03c3 deviation",
      "metadata": {
        "zscore": 2.8040871736247306,
        "current_volume": 21626291,
        "mean_volume": 11564568.05263158
      }
    },
    {
      "signal_type": "volume_anomaly",
      "symbol": "AAPL",
      "timestamp": "2025-09-14T12:16:12.056046",
      "strength": 0.8754589042353225,
      "confidence": 1.0,
      "description": "Volume anomaly detected: 4.07\u03c3 deviation",
      "metadata": {
        "zscore": 4.0679593642236,
        "current_volume": 229989890,
        "mean_volume": 104896643.42105263
      }
    },
    {
      "signal_type": "high_volume",
      "symbol": "AAPL",
      "timestamp": "2025-09-14T12:16:12.056093",
      "strength": 0.4888744619933754,
      "confidence": 0.35638682919086334,
      "description": "High volume: 2.07x average",
      "metadata": {
        "volume_ratio": 2.06916048757259,
        "interpretation": "increased_interest"
      }
    },
    {
      "signal_type": "volume_anomaly",
      "symbol": "NFLX",
      "timestamp": "2025-09-14T12:16:12.059691",
      "strength": 0.7327756947032078,
      "confidence": 0.7010217934061826,
      "description": "Volume anomaly detected: 2.80\u03c3 deviation",
      "metadata": {
        "zscore": 2.8040871736247306,
        "current_volume": 21626291,
        "mean_volume": 11564568.05263158
      }
    },
    {
      "signal_type": "volume_anomaly",
      "symbol": "AAPL",
      "timestamp": "2025-09-14T12:16:12.066384",
      "strength": 0.8754589042353225,
      "confidence": 1.0,
      "description": "Volume anomaly detected: 4.07\u03c3 deviation",
      "metadata": {
        "zscore": 4.0679593642236,
        "current_volume": 229989890,
        "mean_volume": 104896643.42105263
      }
    },
    {
      "signal_type": "high_volume",
      "symbol": "AAPL",
      "timestamp": "2025-09-14T12:16:12.066432",
      "strength": 0.4888744619933754,
      "confidence": 0.35638682919086334,
      "description": "High volume: 2.07x average",
      "metadata": {
        "volume_ratio": 2.06916048757259,
        "interpretation": "increased_interest"
      }
    },
    {
      "signal_type": "volume_anomaly",
      "symbol": "NFLX",
      "timestamp": "2025-09-14T12:16:12.068396",
      "strength": 0.7327756947032078,
      "confidence": 0.7010217934061826,
      "description": "Volume anomaly detected: 2.80\u03c3 deviation",
      "metadata": {
        "zscore": 2.8040871736247306,
        "current_volume": 21626291,
        "mean_volume": 11564568.05263158
      }
    },
    {
      "signal_type": "volume_anomaly",
      "symbol": "AAPL",
      "timestamp": "2025-09-14T12:16:12.073895",
      "strength": 0.8754589042353225,
      "confidence": 1.0,
      "description": "Volume anomaly detected: 4.07\u03c3 deviation",
      "metadata": {
        "zscore": 4.0679593642236,
        "current_volume": 229989890,
        "mean_volume": 104896643.42105263
      }
    },
    {
      "signal_type": "high_volume",
      "symbol": "AAPL",
      "timestamp": "2025-09-14T12:16:12.073936",
      "strength": 0.4888744619933754,
      "confidence": 0.35638682919086334,
      "description": "High volume: 2.07x average",
      "metadata": {
        "volume_ratio": 2.06916048757259,
        "interpretation": "increased_interest"
      }
    },
    {
      "signal_type": "volume_anomaly",
      "symbol": "NFLX",
      "timestamp": "2025-09-14T12:16:12.075539",
      "strength": 0.7327756947032078,
      "confidence": 0.7010217934061826,
      "description": "Volume anomaly detected: 2.80\u03c3 deviation",
      "metadata": {
        "zscore": 2.8040871736247306,
        "current_volume": 21626291,
        "mean_volume": 11564568.05263158
      }
    },
    {
      "signal_type": "volume_anomaly",
      "symbol": "AAPL",
      "timestamp": "2025-09-14T12:16:12.078865",
      "strength": 0.8754589042353225,
      "confidence": 1.0,
      "description": "Volume anomaly detected: 4.07\u03c3 deviation",
      "metadata": {
        "zscore": 4.0679593642236,
        "current_volume": 229989890,
        "mean_volume": 104896643.42105263
      }
    },
    {
      "signal_type": "high_volume",
      "symbol": "AAPL",
      "timestamp": "2025-09-14T12:16:12.078906",
      "strength": 0.4888744619933754,
      "confidence": 0.35638682919086334,
      "description": "High volume: 2.07x average",
      "metadata": {
        "volume_ratio": 2.06916048757259,
        "interpretation": "increased_interest"
      }
    },
    {
      "signal_type": "volume_anomaly",
      "symbol": "NFLX",
      "timestamp": "2025-09-14T12:16:12.080434",
      "strength": 0.7327756947032078,
      "confidence": 0.7010217934061826,
      "description": "Volume anomaly detected: 2.80\u03c3 deviation",
      "metadata": {
        "zscore": 2.8040871736247306,
        "current_volume": 21626291,
        "mean_volume": 11564568.05263158
      }
    },
    {
      "signal_type": "volume_anomaly",
      "symbol": "AAPL",
      "timestamp": "2025-09-14T12:16:12.087648",
      "strength": 0.8754589042353225,
      "confidence": 1.0,
      "description": "Volume anomaly detected: 4.07\u03c3 deviation",
      "metadata": {
        "zscore": 4.0679593642236,
        "current_volume": 229989890,
        "mean_volume": 104896643.42105263
      }
    },
    {
      "signal_type": "high_volume",
      "symbol": "AAPL",
      "timestamp": "2025-09-14T12:16:12.087688",
      "strength": 0.4888744619933754,
      "confidence": 0.35638682919086334,
      "description": "High volume: 2.07x average",
      "metadata": {
        "volume_ratio": 2.06916048757259,
        "interpretation": "increased_interest"
      }
    },
    {
      "signal_type": "volume_anomaly",
      "symbol": "NFLX",
      "timestamp": "2025-09-14T12:16:12.089230",
      "strength": 0.7327756947032078,
      "confidence": 0.7010217934061826,
      "description": "Volume anomaly detected: 2.80\u03c3 deviation",
      "metadata": {
        "zscore": 2.8040871736247306,
        "current_volume": 21626291,
        "mean_volume": 11564568.05263158
      }
    },
    {
      "signal_type": "volume_anomaly",
      "symbol": "AAPL",
      "timestamp": "2025-09-14T12:16:12.093622",
      "strength": 0.8754589042353225,
      "confidence": 1.0,
      "description": "Volume anomaly detected: 4.07\u03c3 deviation",
      "metadata": {
        "zscore": 4.0679593642236,
        "current_volume": 229989890,
        "mean_volume": 104896643.42105263
      }
    },
    {
      "signal_type": "high_volume",
      "symbol": "AAPL",
      "timestamp": "2025-09-14T12:16:12.093654",
      "strength": 0.4888744619933754,
      "confidence": 0.35638682919086334,
      "description": "High volume: 2.07x average",
      "metadata": {
        "volume_ratio": 2.06916048757259,
        "interpretation": "increased_interest"
      }
    },
    {
      "signal_type": "volume_anomaly",
      "symbol": "NFLX",
      "timestamp": "2025-09-14T12:16:12.104640",
      "strength": 0.7327756947032078,
      "confidence": 0.7010217934061826,
      "description": "Volume anomaly detected: 2.80\u03c3 deviation",
      "metadata": {
        "zscore": 2.8040871736247306,
        "current_volume": 21626291,
        "mean_volume": 11564568.05263158
      }
    },
    {
      "signal_type": "volume_anomaly",
      "symbol": "AAPL",
      "timestamp": "2025-09-14T12:16:12.108532",
      "strength": 0.8754589042353225,
      "confidence": 1.0,
      "description": "Volume anomaly detected: 4.07\u03c3 deviation",
      "metadata": {
        "zscore": 4.0679593642236,
        "current_volume": 229989890,
        "mean_volume": 104896643.42105263
      }
    },
    {
      "signal_type": "high_volume",
      "symbol": "AAPL",
      "timestamp": "2025-09-14T12:16:12.108576",
      "strength": 0.4888744619933754,
      "confidence": 0.35638682919086334,
      "description": "High volume: 2.07x average",
      "metadata": {
        "volume_ratio": 2.06916048757259,
        "interpretation": "increased_interest"
      }
    },
    {
      "signal_type": "volume_anomaly",
      "symbol": "NFLX",
      "timestamp": "2025-09-14T12:16:12.110432",
      "strength": 0.7327756947032078,
      "confidence": 0.7010217934061826,
      "description": "Volume anomaly detected: 2.80\u03c3 deviation",
      "metadata": {
        "zscore": 2.8040871736247306,
        "current_volume": 21626291,
        "mean_volume": 11564568.05263158
      }
    },
    {
      "signal_type": "volume_anomaly",
      "symbol": "AAPL",
      "timestamp": "2025-09-14T12:16:12.115028",
      "strength": 0.8754589042353225,
      "confidence": 1.0,
      "description": "Volume anomaly detected: 4.07\u03c3 deviation",
      "metadata": {
        "zscore": 4.0679593642236,
        "current_volume": 229989890,
        "mean_volume": 104896643.42105263
      }
    },
    {
      "signal_type": "high_volume",
      "symbol": "AAPL",
      "timestamp": "2025-09-14T12:16:12.115072",
      "strength": 0.4888744619933754,
      "confidence": 0.35638682919086334,
      "description": "High volume: 2.07x average",
      "metadata": {
        "volume_ratio": 2.06916048757259,
        "interpretation": "increased_interest"
      }
    },
    {
      "signal_type": "volume_anomaly",
      "symbol": "NFLX",
      "timestamp": "2025-09-14T12:16:12.117856",
      "strength": 0.7327756947032078,
      "confidence": 0.7010217934061826,
      "description": "Volume anomaly detected: 2.80\u03c3 deviation",
      "metadata": {
        "zscore": 2.8040871736247306,
        "current_volume": 21626291,
        "mean_volume": 11564568.05263158
      }
    },
    {
      "signal_type": "volume_anomaly",
      "symbol": "AAPL",
      "timestamp": "2025-09-14T12:16:12.126911",
      "strength": 0.8754589042353225,
      "confidence": 1.0,
      "description": "Volume anomaly detected: 4.07\u03c3 deviation",
      "metadata": {
        "zscore": 4.0679593642236,
        "current_volume": 229989890,
        "mean_volume": 104896643.42105263
      }
    },
    {
      "signal_type": "high_volume",
      "symbol": "AAPL",
      "timestamp": "2025-09-14T12:16:12.126955",
      "strength": 0.4888744619933754,
      "confidence": 0.35638682919086334,
      "description": "High volume: 2.07x average",
      "metadata": {
        "volume_ratio": 2.06916048757259,
        "interpretation": "increased_interest"
      }
    },
    {
      "signal_type": "volume_anomaly",
      "symbol": "NFLX",
      "timestamp": "2025-09-14T12:16:12.128843",
      "strength": 0.7327756947032078,
      "confidence": 0.7010217934061826,
      "description": "Volume anomaly detected: 2.80\u03c3 deviation",
      "metadata": {
        "zscore": 2.8040871736247306,
        "current_volume": 21626291,
        "mean_volume": 11564568.05263158
      }
    },
    {
      "signal_type": "volume_anomaly",
      "symbol": "AAPL",
      "timestamp": "2025-09-14T12:16:12.134976",
      "strength": 0.8754589042353225,
      "confidence": 1.0,
      "description": "Volume anomaly detected: 4.07\u03c3 deviation",
      "metadata": {
        "zscore": 4.0679593642236,
        "current_volume": 229989890,
        "mean_volume": 104896643.42105263
      }
    },
    {
      "signal_type": "high_volume",
      "symbol": "AAPL",
      "timestamp": "2025-09-14T12:16:12.135022",
      "strength": 0.4888744619933754,
      "confidence": 0.35638682919086334,
      "description": "High volume: 2.07x average",
      "metadata": {
        "volume_ratio": 2.06916048757259,
        "interpretation": "increased_interest"
      }
    },
    {
      "signal_type": "volume_anomaly",
      "symbol": "NFLX",
      "timestamp": "2025-09-14T12:16:12.138405",
      "strength": 0.7327756947032078,
      "confidence": 0.7010217934061826,
      "description": "Volume anomaly detected: 2.80\u03c3 deviation",
      "metadata": {
        "zscore": 2.8040871736247306,
        "current_volume": 21626291,
        "mean_volume": 11564568.05263158
      }
    },
    {
      "signal_type": "volume_anomaly",
      "symbol": "AAPL",
      "timestamp": "2025-09-14T12:16:12.144819",
      "strength": 0.8754589042353225,
      "confidence": 1.0,
      "description": "Volume anomaly detected: 4.07\u03c3 deviation",
      "metadata": {
        "zscore": 4.0679593642236,
        "current_volume": 229989890,
        "mean_volume": 104896643.42105263
      }
    },
    {
      "signal_type": "high_volume",
      "symbol": "AAPL",
      "timestamp": "2025-09-14T12:16:12.144873",
      "strength": 0.4888744619933754,
      "confidence": 0.35638682919086334,
      "description": "High volume: 2.07x average",
      "metadata": {
        "volume_ratio": 2.06916048757259,
        "interpretation": "increased_interest"
      }
    },
    {
      "signal_type": "volume_anomaly",
      "symbol": "NFLX",
      "timestamp": "2025-09-14T12:16:12.147134",
      "strength": 0.7327756947032078,
      "confidence": 0.7010217934061826,
      "description": "Volume anomaly detected: 2.80\u03c3 deviation",
      "metadata": {
        "zscore": 2.8040871736247306,
        "current_volume": 21626291,
        "mean_volume": 11564568.05263158
      }
    },
    {
      "signal_type": "volume_anomaly",
      "symbol": "PG",
      "timestamp": "2025-09-14T12:16:13.156480",
      "strength": 0.7610380664083883,
      "confidence": 0.7490079221440639,
      "description": "Volume anomaly detected: 3.00\u03c3 deviation",
      "metadata": {
        "zscore": 2.9960316885762555,
        "current_volume": 23207323,
        "mean_volume": 13355588.05263158
      }
    },
    {
      "signal_type": "volume_anomaly",
      "symbol": "KO",
      "timestamp": "2025-09-14T12:16:13.156790",
      "strength": 0.9583768441299434,
      "confidence": 1.0,
      "description": "Volume anomaly detected: 5.78\u03c3 deviation",
      "metadata": {
        "zscore": 5.776821936719144,
        "current_volume": 47829306,
        "mean_volume": 20787562.736842107
      }
    },
    {
      "signal_type": "high_volume",
      "symbol": "KO",
      "timestamp": "2025-09-14T12:16:13.156823",
      "strength": 0.5227911894576622,
      "confidence": 0.38678202856315275,
      "description": "High volume: 2.16x average",
      "metadata": {
        "volume_ratio": 2.1603460856894583,
        "interpretation": "increased_interest"
      }
    },
    {
      "signal_type": "rsi_overbought",
      "symbol": "AAPL",
      "timestamp": "2025-09-14T12:16:14.158234",
      "strength": -0.8,
      "confidence": 1.0,
      "description": "RSI overbought: 100.0",
      "metadata": {
        "rsi": 100.0
      }
    },
    {
      "signal_type": "rsi_overbought",
      "symbol": "GOOGL",
      "timestamp": "2025-09-14T12:16:14.158742",
      "strength": -0.8,
      "confidence": 1.0,
      "description": "RSI overbought: 100.0",
      "metadata": {
        "rsi": 100.0
      }
    },
    {
      "signal_type": "rsi_overbought",
      "symbol": "MSFT",
      "timestamp": "2025-09-14T12:16:14.159020",
      "strength": -0.8,
      "confidence": 1.0,
      "description": "RSI overbought: 100.0",
      "metadata": {
        "rsi": 100.0
      }
    },
    {
      "signal_type": "rsi_overbought",
      "symbol": "AMZN",
      "timestamp": "2025-09-14T12:16:14.159216",
      "strength": -0.8,
      "confidence": 1.0,
      "description": "RSI overbought: 100.0",
      "metadata": {
        "rsi": 100.0
      }
    },
    {
      "signal_type": "rsi_overbought",
      "symbol": "TSLA",
      "timestamp": "2025-09-14T12:16:14.159517",
      "strength": -0.8,
      "confidence": 1.0,
      "description": "RSI overbought: 100.0",
      "metadata": {
        "rsi": 100.0
      }
    },
    {
      "signal_type": "rsi_overbought",
      "symbol": "NVDA",
      "timestamp": "2025-09-14T12:16:14.159729",
      "strength": -0.8,
      "confidence": 1.0,
      "description": "RSI overbought: 100.0",
      "metadata": {
        "rsi": 100.0
      }
    },
    {
      "signal_type": "rsi_overbought",
      "symbol": "META",
      "timestamp": "2025-09-14T12:16:14.159921",
      "strength": -0.8,
      "confidence": 1.0,
      "description": "RSI overbought: 100.0",
      "metadata": {
        "rsi": 100.0
      }
    },
    {
      "signal_type": "rsi_overbought",
      "symbol": "NFLX",
      "timestamp": "2025-09-14T12:16:14.160109",
      "strength": -0.8,
      "confidence": 1.0,
      "description": "RSI overbought: 100.0",
      "metadata": {
        "rsi": 100.0
      }
    },
    {
      "signal_type": "rsi_overbought",
      "symbol": "JPM",
      "timestamp": "2025-09-14T12:16:14.160292",
      "strength": -0.8,
      "confidence": 1.0,
      "description": "RSI overbought: 100.0",
      "metadata": {
        "rsi": 100.0
      }
    },
    {
      "signal_type": "rsi_overbought",
      "symbol": "BAC",
      "timestamp": "2025-09-14T12:16:14.160469",
      "strength": -0.8,
      "confidence": 1.0,
      "description": "RSI overbought: 100.0",
      "metadata": {
        "rsi": 100.0
      }
    },
    {
      "signal_type": "rsi_overbought",
      "symbol": "JNJ",
      "timestamp": "2025-09-14T12:16:14.160643",
      "strength": -0.8,
      "confidence": 1.0,
      "description": "RSI overbought: 100.0",
      "metadata": {
        "rsi": 100.0
      }
    },
    {
      "signal_type": "rsi_overbought",
      "symbol": "PFE",
      "timestamp": "2025-09-14T12:16:14.160818",
      "strength": -0.8,
      "confidence": 1.0,
      "description": "RSI overbought: 100.0",
      "metadata": {
        "rsi": 100.0
      }
    },
    {
      "signal_type": "rsi_overbought",
      "symbol": "XOM",
      "timestamp": "2025-09-14T12:16:14.160989",
      "strength": -0.8,
      "confidence": 1.0,
      "description": "RSI overbought: 100.0",
      "metadata": {
        "rsi": 100.0
      }
    },
    {
      "signal_type": "rsi_overbought",
      "symbol": "CVX",
      "timestamp": "2025-09-14T12:16:14.161181",
      "strength": -0.8,
      "confidence": 1.0,
      "description": "RSI overbought: 100.0",
      "metadata": {
        "rsi": 100.0
      }
    },
    {
      "signal_type": "rsi_overbought",
      "symbol": "WMT",
      "timestamp": "2025-09-14T12:16:14.161318",
      "strength": -0.8,
      "confidence": 1.0,
      "description": "RSI overbought: 100.0",
      "metadata": {
        "rsi": 100.0
      }
    },
    {
      "signal_type": "rsi_overbought",
      "symbol": "HD",
      "timestamp": "2025-09-14T12:16:14.161455",
      "strength": -0.8,
      "confidence": 1.0,
      "description": "RSI overbought: 100.0",
      "metadata": {
        "rsi": 100.0
      }
    },
    {
      "signal_type": "rsi_overbought",
      "symbol": "PG",
      "timestamp": "2025-09-14T12:16:14.161591",
      "strength": -0.8,
      "confidence": 1.0,
      "description": "RSI overbought: 100.0",
      "metadata": {
        "rsi": 100.0
      }
    },
    {
      "signal_type": "rsi_overbought",
      "symbol": "KO",
      "timestamp": "2025-09-14T12:16:14.161727",
      "strength": -0.8,
      "confidence": 1.0,
      "description": "RSI overbought: 100.0",
      "metadata": {
        "rsi": 100.0
      }
    },
    {
      "signal_type": "rsi_overbought",
      "symbol": "DIS",
      "timestamp": "2025-09-14T12:16:14.161862",
      "strength": -0.8,
      "confidence": 1.0,
      "description": "RSI overbought: 100.0",
      "metadata": {
        "rsi": 100.0
      }
    },
    {
      "signal_type": "rsi_overbought",
      "symbol": "V",
      "timestamp": "2025-09-14T12:16:14.161997",
      "strength": -0.8,
      "confidence": 1.0,
      "description": "RSI overbought: 100.0",
      "metadata": {
        "rsi": 100.0
      }
    }
  ],
  "heat_analysis": {
    "AAPL": {
      "symbol": "AAPL",
      "current_heat": 8.45,
      "heat_trend": "stable",
      "heat_velocity": 0.12099999999999969,
      "propagation_strength": 0.08449999999999999,
      "influenced_symbols": [],
      "analysis_timestamp": "2025-09-14T12:16:14.158713"
    },
    "GOOGL": {
      "symbol": "GOOGL",
      "current_heat": 7.61,
      "heat_trend": "stable",
      "heat_velocity": -0.008000000000001214,
      "propagation_strength": 0.0761,
      "influenced_symbols": [],
      "analysis_timestamp": "2025-09-14T12:16:14.159004"
    },
    "MSFT": {
      "symbol": "MSFT",
      "current_heat": 8.43,
      "heat_trend": "stable",
      "heat_velocity": -0.190000000000001,
      "propagation_strength": 0.0843,
      "influenced_symbols": [],
      "analysis_timestamp": "2025-09-14T12:16:14.159202"
    },
    "AMZN": {
      "symbol": "AMZN",
      "current_heat": 7.58,
      "heat_trend": "stable",
      "heat_velocity": 0.10499999999999954,
      "propagation_strength": 0.0758,
      "influenced_symbols": [],
      "analysis_timestamp": "2025-09-14T12:16:14.159497"
    },
    "TSLA": {
      "symbol": "TSLA",
      "current_heat": 4.79,
      "heat_trend": "stable",
      "heat_velocity": -0.041000000000000834,
      "propagation_strength": 0.0479,
      "influenced_symbols": [],
      "analysis_timestamp": "2025-09-14T12:16:14.159714"
    },
    "NVDA": {
      "symbol": "NVDA",
      "current_heat": 7.1,
      "heat_trend": "stable",
      "heat_velocity": -0.061000000000001116,
      "propagation_strength": 0.071,
      "influenced_symbols": [],
      "analysis_timestamp": "2025-09-14T12:16:14.159907"
    },
    "META": {
      "symbol": "META",
      "current_heat": 6.12,
      "heat_trend": "stable",
      "heat_velocity": -0.13500000000000076,
      "propagation_strength": 0.061200000000000004,
      "influenced_symbols": [],
      "analysis_timestamp": "2025-09-14T12:16:14.160096"
    },
    "NFLX": {
      "symbol": "NFLX",
      "current_heat": 5.65,
      "heat_trend": "stable",
      "heat_velocity": 0.10599999999999975,
      "propagation_strength": 0.0565,
      "influenced_symbols": [],
      "analysis_timestamp": "2025-09-14T12:16:14.160279"
    },
    "JPM": {
      "symbol": "JPM",
      "current_heat": 4.36,
      "heat_trend": "stable",
      "heat_velocity": -0.057000000000000356,
      "propagation_strength": 0.0436,
      "influenced_symbols": [],
      "analysis_timestamp": "2025-09-14T12:16:14.160456"
    },
    "BAC": {
      "symbol": "BAC",
      "current_heat": 4.45,
      "heat_trend": "stable",
      "heat_velocity": -0.13900000000000096,
      "propagation_strength": 0.044500000000000005,
      "influenced_symbols": [],
      "analysis_timestamp": "2025-09-14T12:16:14.160630"
    },
    "JNJ": {
      "symbol": "JNJ",
      "current_heat": 3.63,
      "heat_trend": "stable",
      "heat_velocity": -0.036000000000000296,
      "propagation_strength": 0.0363,
      "influenced_symbols": [],
      "analysis_timestamp": "2025-09-14T12:16:14.160804"
    },
    "PFE": {
      "symbol": "PFE",
      "current_heat": 3.95,
      "heat_trend": "stable",
      "heat_velocity": -0.03600000000000058,
      "propagation_strength": 0.0395,
      "influenced_symbols": [],
      "analysis_timestamp": "2025-09-14T12:16:14.160976"
    },
    "XOM": {
      "symbol": "XOM",
      "current_heat": 4.6,
      "heat_trend": "stable",
      "heat_velocity": -0.1250000000000013,
      "propagation_strength": 0.046,
      "influenced_symbols": [],
      "analysis_timestamp": "2025-09-14T12:16:14.161170"
    },
    "CVX": {
      "symbol": "CVX",
      "current_heat": 4.39,
      "heat_trend": "stable",
      "heat_velocity": -0.05900000000000095,
      "propagation_strength": 0.043899999999999995,
      "influenced_symbols": [],
      "analysis_timestamp": "2025-09-14T12:16:14.161308"
    },
    "WMT": {
      "symbol": "WMT",
      "current_heat": 4.62,
      "heat_trend": "stable",
      "heat_velocity": -0.019000000000000364,
      "propagation_strength": 0.0462,
      "influenced_symbols": [],
      "analysis_timestamp": "2025-09-14T12:16:14.161445"
    },
    "HD": {
      "symbol": "HD",
      "current_heat": 4.26,
      "heat_trend": "stable",
      "heat_velocity": -0.1610000000000002,
      "propagation_strength": 0.0426,
      "influenced_symbols": [],
      "analysis_timestamp": "2025-09-14T12:16:14.161581"
    },
    "PG": {
      "symbol": "PG",
      "current_heat": 4.39,
      "heat_trend": "stable",
      "heat_velocity": 0.024999999999999193,
      "propagation_strength": 0.043899999999999995,
      "influenced_symbols": [],
      "analysis_timestamp": "2025-09-14T12:16:14.161717"
    },
    "KO": {
      "symbol": "KO",
      "current_heat": 4.18,
      "heat_trend": "stable",
      "heat_velocity": -0.057000000000001244,
      "propagation_strength": 0.0418,
      "influenced_symbols": [],
      "analysis_timestamp": "2025-09-14T12:16:14.161851"
    },
    "DIS": {
      "symbol": "DIS",
      "current_heat": 4.15,
      "heat_trend": "stable",
      "heat_velocity": -0.2550000000000005,
      "propagation_strength": 0.0415,
      "influenced_symbols": [],
      "analysis_timestamp": "2025-09-14T12:16:14.161987"
    },
    "V": {
      "symbol": "V",
      "current_heat": 4.07,
      "heat_trend": "stable",
      "heat_velocity": -0.15400000000000064,
      "propagation_strength": 0.0407,
      "influenced_symbols": [],
      "analysis_timestamp": "2025-09-14T12:16:14.162121"
    }
  },
  "analytics_status": {
    "tracked_symbols": 20,
    "data_points_per_symbol": {
      "AAPL": 100,
      "GOOGL": 100,
      "MSFT": 100,
      "AMZN": 100,
      "TSLA": 100
    },
    "active_signals": 178,
    "signal_history_size": 500,
    "heat_analysis_cache_size": 20,
    "last_analysis_time": "2025-09-14T12:16:14.162132",
    "analysis_intervals": {
      "fast": 1.0,
      "medium": 5.0,
      "slow": 30.0
    }
  }
}